Workbook

Sheet Summary
A1: Features, phases and status - ATIP-DEV, bkesari, bkesari-platform
A2: Status as of 2026-10-09, from the GitHub repositories (sanjaymorankar-debug) and a fresh clone. 'Phases' rolls every feature up by app and phase; the counts are formulas over 'All Features'.
A4: Repositories
A5: Repo | B5: What it is | C5: Default branch | D5: Latest commit | E5: Date | F5: Latest commit message | G5: GitHub
A6: ATIP-DEV | B6: ATIP - AI Trading Intelligence Platform (Python) | C6: master | D6: d01705e | E6: 2026-10-09 | F6: Merge pull request #8: MySQL runtime: translate what cannot translate, quote what MySQL reserves | G6: https://github.com/sanjaymorankar-debug/ATIP-DEV
A7: bkesari | B7: Bkesari shop & milk marketplace (Next.js) | C7: main | D7: 3cfd098 | E7: 2026-10-09 | F7: Merge pull request #13: fill blank test secrets too, so tests pass after cp .env.example .env | G7: https://github.com/sanjaymorankar-debug/bkesari
A8: bkesari-platform | B8: bkesari.com portal + Education (Node / Laravel) | C8: main | D8: 362cbc8 | E8: 2026-10-09 | F8: Merge pull request #4: local MySQL setup script, and the Mac guide and status workbook brought up to date | G8: https://github.com/sanjaymorankar-debug/bkesari-platform
A10: Features by status (from 'All Features')
A11: Repo | B11: Total features | C11: On GitHub default branch | D11: Not merged | E11: Completed | F11: Implemented, not verified | G11: Blocked | H11: In progress | I11: In review (open PR) | J11: In review (draft PR) | K11: Superseded | L11: Not started
A12: ATIP-DEV | B12: =COUNTIF('All Features'!$A$2:$A$423,$A12) -> 337 | C12: =COUNTIFS('All Features'!$A$2:$A$423,$A12,'All Features'!$L$2:$L$423,"Yes") -> 337 | D12: =COUNTIFS('All Features'!$A$2:$A$423,$A12,'All Features'!$L$2:$L$423,"No") -> 0 | E12: =COUNTIFS('All Features'!$A$2:$A$423,$A12,'All Features'!$O$2:$O$423,"COMPLETED") -> 130 | F12: =COUNTIFS('All Features'!$A$2:$A$423,$A12,'All Features'!$O$2:$O$423,"IMPLEMENTED BUT NOT VERIFIED") -> 197 | G12: =COUNTIFS('All Features'!$A$2:$A$423,$A12,'All Features'!$O$2:$O$423,"BLOCKED") -> 9 | H12: =COUNTIFS('All Features'!$A$2:$A$423,$A12,'All Features'!$O$2:$O$423,"IN PROGRESS") -> 1 | I12: =COUNTIFS('All Features'!$A$2:$A$423,$A12,'All Features'!$O$2:$O$423,"IN REVIEW (open PR)") -> 0 | J12: =COUNTIFS('All Features'!$A$2:$A$423,$A12,'All Features'!$O$2:$O$423,"IN REVIEW (draft PR)") -> 0 | K12: =COUNTIFS('All Features'!$A$2:$A$423,$A12,'All Features'!$O$2:$O$423,"SUPERSEDED") -> 0 | L12: =COUNTIFS('All Features'!$A$2:$A$423,$A12,'All Features'!$O$2:$O$423,"NOT STARTED") -> 0
A13: bkesari | B13: =COUNTIF('All Features'!$A$2:$A$423,$A13) -> 33 | C13: =COUNTIFS('All Features'!$A$2:$A$423,$A13,'All Features'!$L$2:$L$423,"Yes") -> 32 | D13: =COUNTIFS('All Features'!$A$2:$A$423,$A13,'All Features'!$L$2:$L$423,"No") -> 1 | E13: =COUNTIFS('All Features'!$A$2:$A$423,$A13,'All Features'!$O$2:$O$423,"COMPLETED") -> 32 | F13: =COUNTIFS('All Features'!$A$2:$A$423,$A13,'All Features'!$O$2:$O$423,"IMPLEMENTED BUT NOT VERIFIED") -> 0 | G13: =COUNTIFS('All Features'!$A$2:$A$423,$A13,'All Features'!$O$2:$O$423,"BLOCKED") -> 0 | H13: =COUNTIFS('All Features'!$A$2:$A$423,$A13,'All Features'!$O$2:$O$423,"IN PROGRESS") -> 0 | I13: =COUNTIFS('All Features'!$A$2:$A$423,$A13,'All Features'!$O$2:$O$423,"IN REVIEW (open PR)") -> 1 | J13: =COUNTIFS('All Features'!$A$2:$A$423,$A13,'All Features'!$O$2:$O$423,"IN REVIEW (draft PR)") -> 0 | K13: =COUNTIFS('All Features'!$A$2:$A$423,$A13,'All Features'!$O$2:$O$423,"SUPERSEDED") -> 0 | L13: =COUNTIFS('All Features'!$A$2:$A$423,$A13,'All Features'!$O$2:$O$423,"NOT STARTED") -> 0
A14: bkesari-platform | B14: =COUNTIF('All Features'!$A$2:$A$423,$A14) -> 52 | C14: =COUNTIFS('All Features'!$A$2:$A$423,$A14,'All Features'!$L$2:$L$423,"Yes") -> 39 | D14: =COUNTIFS('All Features'!$A$2:$A$423,$A14,'All Features'!$L$2:$L$423,"No") -> 13 | E14: =COUNTIFS('All Features'!$A$2:$A$423,$A14,'All Features'!$O$2:$O$423,"COMPLETED") -> 38 | F14: =COUNTIFS('All Features'!$A$2:$A$423,$A14,'All Features'!$O$2:$O$423,"IMPLEMENTED BUT NOT VERIFIED") -> 0 | G14: =COUNTIFS('All Features'!$A$2:$A$423,$A14,'All Features'!$O$2:$O$423,"BLOCKED") -> 0 | H14: =COUNTIFS('All Features'!$A$2:$A$423,$A14,'All Features'!$O$2:$O$423,"IN PROGRESS") -> 0 | I14: =COUNTIFS('All Features'!$A$2:$A$423,$A14,'All Features'!$O$2:$O$423,"IN REVIEW (open PR)") -> 1 | J14: =COUNTIFS('All Features'!$A$2:$A$423,$A14,'All Features'!$O$2:$O$423,"IN REVIEW (draft PR)") -> 0 | K14: =COUNTIFS('All Features'!$A$2:$A$423,$A14,'All Features'!$O$2:$O$423,"SUPERSEDED") -> 1 | L14: =COUNTIFS('All Features'!$A$2:$A$423,$A14,'All Features'!$O$2:$O$423,"NOT STARTED") -> 12
A15: TOTAL | B15: =SUM(B12:B14) -> 422 | C15: =SUM(C12:C14) -> 408 | D15: =SUM(D12:D14) -> 14 | E15: =SUM(E12:E14) -> 200 | F15: =SUM(F12:F14) -> 197 | G15: =SUM(G12:G14) -> 9 | H15: =SUM(H12:H14) -> 1 | I15: =SUM(I12:I14) -> 2 | ... L15: =SUM(L12:L14) -> 12
A16: Check: the status columns add up to 'Total features' | E16: =IF(SUM(E15:L15)=B15,"OK","MISMATCH") -> OK
A18: Pull requests (from 'Pull Requests')
A19: Repo | B19: Total PRs | C19: Merged | D19: Open - not merged | E19: Draft - not merged
A20: ATIP-DEV | B20: =COUNTIF('Pull Requests'!$A$2:$A$28,$A20) -> 8 | C20: =COUNTIFS('Pull Requests'!$A$2:$A$28,$A20,'Pull Requests'!$F$2:$F$28,"Merged") -> 8 | D20: =COUNTIFS('Pull Requests'!$A$2:$A$28,$A20,'Pull Requests'!$F$2:$F$28,"Open - not merged") -> 0 | E20: =COUNTIFS('Pull Requests'!$A$2:$A$28,$A20,'Pull Requests'!$F$2:$F$28,"Draft - not merged") -> 0
A21: bkesari | B21: =COUNTIF('Pull Requests'!$A$2:$A$28,$A21) -> 14 | C21: =COUNTIFS('Pull Requests'!$A$2:$A$28,$A21,'Pull Requests'!$F$2:$F$28,"Merged") -> 13 | D21: =COUNTIFS('Pull Requests'!$A$2:$A$28,$A21,'Pull Requests'!$F$2:$F$28,"Open - not merged") -> 1 | E21: =COUNTIFS('Pull Requests'!$A$2:$A$28,$A21,'Pull Requests'!$F$2:$F$28,"Draft - not merged") -> 0
A22: bkesari-platform | B22: =COUNTIF('Pull Requests'!$A$2:$A$28,$A22) -> 5 | C22: =COUNTIFS('Pull Requests'!$A$2:$A$28,$A22,'Pull Requests'!$F$2:$F$28,"Merged") -> 4 | D22: =COUNTIFS('Pull Requests'!$A$2:$A$28,$A22,'Pull Requests'!$F$2:$F$28,"Open - not merged") -> 1 | E22: =COUNTIFS('Pull Requests'!$A$2:$A$28,$A22,'Pull Requests'!$F$2:$F$28,"Draft - not merged") -> 0
A23: TOTAL | B23: =SUM(B20:B22) -> 27 | C23: =SUM(C20:C22) -> 25 | D23: =SUM(D20:D22) -> 2 | E23: =SUM(E20:E22) -> 0
A25: Branches on GitHub (from 'Branches')
A26: Repo | B26: Branches | C26: Fully merged | D26: Merged (same changes) | E26: NOT merged
A27: ATIP-DEV | B27: =COUNTIF(Branches!$A$2:$A$75,$A27) -> 64 | C27: =COUNTIFS(Branches!$A$2:$A$75,$A27,Branches!$H$2:$H$75,"Fully merged") -> 60 | D27: =COUNTIFS(Branches!$A$2:$A$75,$A27,Branches!$H$2:$H$75,"Merged (same changes already in default)") -> 1 | E27: =COUNTIFS(Branches!$A$2:$A$75,$A27,Branches!$H$2:$H$75,"NOT merged") -> 2
A28: bkesari | B28: =COUNTIF(Branches!$A$2:$A$75,$A28) -> 5 | C28: =COUNTIFS(Branches!$A$2:$A$75,$A28,Branches!$H$2:$H$75,"Fully merged") -> 3 | D28: =COUNTIFS(Branches!$A$2:$A$75,$A28,Branches!$H$2:$H$75,"Merged (same changes already in default)") -> 0 | E28: =COUNTIFS(Branches!$A$2:$A$75,$A28,Branches!$H$2:$H$75,"NOT merged") -> 1
A29: bkesari-platform | B29: =COUNTIF(Branches!$A$2:$A$75,$A29) -> 5 | C29: =COUNTIFS(Branches!$A$2:$A$75,$A29,Branches!$H$2:$H$75,"Fully merged") -> 3 | D29: =COUNTIFS(Branches!$A$2:$A$75,$A29,Branches!$H$2:$H$75,"Merged (same changes already in default)") -> 0 | E29: =COUNTIFS(Branches!$A$2:$A$75,$A29,Branches!$H$2:$H$75,"NOT merged") -> 1
A30: TOTAL | B30: =SUM(B27:B29) -> 74 | C30: =SUM(C27:C29) -> 66 | D30: =SUM(D27:D29) -> 1 | E30: =SUM(E27:E29) -> 4
A32: Read this first
A33: 1. All five PRs that were open on 2026-10-08 (ATIP-DEV#8, bkesari#9 and #10, bkesari-platform#1 and #2) are now merged. bkesari#12, #13 and bkesari-platform#4 followed on 2026-10-09. Open now: bkesari#14 and bkesari-platform#5, both opened on 2026-10-09 by another session (test tooling only).
A34: 2. 'Local Git (fresh clone)' is the clone this report was built from, which matches GitHub. It cannot see commits that exist only on your Mac. Run tools/check_local_git.sh on the Mac to list those (see MAC_DEPLOYMENT.md).
A35: 3. ATIP rows come from the repo's own tracker, docs/ATIP_MASTER_TRACKER.csv (331 rows), plus 6 for the macOS / database PRs. 'IMPLEMENTED BUT NOT VERIFIED' means merged, with automated tests, but independent QA / owner UAT is still pending.
A36: 4. 'Phases' gives one row per phase of each app with its counts, % completed and a phase status. To update a status, change it in the Status column of 'All Features' (it has a drop-down); Phases and this sheet recalculate.
A37: 5. BLOCKED ATIP rows are partly built and wait on an owner decision or credential (see the 'Blocker / next action' column).
A38: 6. The branch claude/epic-brown-iurf1w (this report's own working branch) is left out of 'Branches'.
A39: 7. Testing status: bkesari and Education rows show the result of running their suites on 2026-10-09; ATIP rows keep the tracker's own Testing Status. Every suite passed - see 'Test Runs' (run on Linux, not on a Mac).

Sheet Phases
A1: Features by phase
A2: One row per phase of each app. Every count is a formula over 'All Features', so changing a feature's Status there updates its phase here.
A4: Repo | B4: App | C4: Phase # | D4: Phase | E4: From | F4: To | G4: Features | H4: Completed | I4: Implemented, not verified | J4: Blocked | K4: In progress | L4: In review (PR open) | M4: Not started | N4: Superseded | O4: On GitHub default branch | P4: % completed | Q4: Avg completion % (where recorded) | R4: Phase status
A5: ATIP-DEV | B5: ATIP | C5: 0 | D5: Phase 0: Delivered baseline (maintain) | E5: =IF(COUNTIFS('All Features'!$B$2:$B$423,$B5,'All Features'!$C$2:$C$423,$C5,'All Features'!$J$2:$J$423,">0")=0,"",_xlfn.MINIFS('All Features'!$J$2:$J$423,'All Features'!$B$2:$B$423,$B5,'All Features'!$C$2:$C$423,$C5)) -> 46289 | F5: =IF(COUNTIFS('All Features'!$B$2:$B$423,$B5,'All Features'!$C$2:$C$423,$C5,'All Features'!$J$2:$J$423,">0")=0,"",_xlfn.MAXIFS('All Features'!$J$2:$J$423,'All Features'!$B$2:$B$423,$B5,'All Features'!$C$2:$C$423,$C5)) -> 46302 | G5: =COUNTIFS('All Features'!$B$2:$B$423,$B5,'All Features'!$C$2:$C$423,$C5) -> 58 | H5: =COUNTIFS('All Features'!$B$2:$B$423,$B5,'All Features'!$C$2:$C$423,$C5,'All Features'!$O$2:$O$423,"COMPLETED") -> 58 | I5: =COUNTIFS('All Features'!$B$2:$B$423,$B5,'All Features'!$C$2:$C$423,$C5,'All Features'!$O$2:$O$423,"IMPLEMENTED BUT NOT VERIFIED") -> 0 | J5: =COUNTIFS('All Features'!$B$2:$B$423,$B5,'All Features'!$C$2:$C$423,$C5,'All Features'!$O$2:$O$423,"BLOCKED") -> 0 | K5: =COUNTIFS('All Features'!$B$2:$B$423,$B5,'All Features'!$C$2:$C$423,$C5,'All Features'!$O$2:$O$423,"IN PROGRESS") -> 0 | L5: =COUNTIFS('All Features'!$B$2:$B$423,$B5,'All Features'!$C$2:$C$423,$C5,'All Features'!$O$2:$O$423,"IN REVIEW*") -> 0 | M5: =COUNTIFS('All Features'!$B$2:$B$423,$B5,'All Features'!$C$2:$C$423,$C5,'All Features'!$O$2:$O$423,"NOT STARTED") -> 0 | N5: =COUNTIFS('All Features'!$B$2:$B$423,$B5,'All Features'!$C$2:$C$423,$C5,'All Features'!$O$2:$O$423,"SUPERSEDED") -> 0 | O5: =COUNTIFS('All Features'!$B$2:$B$423,$B5,'All Features'!$C$2:$C$423,$C5,'All Features'!$L$2:$L$423,"Yes") -> 58 | P5: =IFERROR((H5+N5)/G5,0) -> 1 | Q5: =IFERROR(AVERAGEIFS('All Features'!$Q$2:$Q$423,'All Features'!$B$2:$B$423,$B5,'All Features'!$C$2:$C$423,$C5),"") -> 0.79913793 | R5: =IF(G5=0,"-",IF(H5+N5=G5,"COMPLETED",IF(M5=G5,"NOT STARTED",IF(H5+I5+N5=G5,"BUILT - VERIFICATION PENDING","IN PROGRESS"&IF(J5>0," - "&J5&" BLOCKED","")&IF(L5>0," - "&L5&" in review",""))))) -> COMPLETED
A6: ATIP-DEV | B6: ATIP | C6: 1 | D6: Phase 1: Foundation | E6: =IF(COUNTIFS('All Features'!$B$2:$B$423,$B6,'All Features'!$C$2:$C$423,$C6,'All Features'!$J$2:$J$423,">0")=0,"",_xlfn.MINIFS('All Features'!$J$2:$J$423,'All Features'!$B$2:$B$423,$B6,'All Features'!$C$2:$C$423,$C6)) -> 46289 | F6: =IF(COUNTIFS('All Features'!$B$2:$B$423,$B6,'All Features'!$C$2:$C$423,$C6,'All Features'!$J$2:$J$423,">0")=0,"",_xlfn.MAXIFS('All Features'!$J$2:$J$423,'All Features'!$B$2:$B$423,$B6,'All Features'!$C$2:$C$423,$C6)) -> 46302 | G6: =COUNTIFS('All Features'!$B$2:$B$423,$B6,'All Features'!$C$2:$C$423,$C6) -> 31 | H6: =COUNTIFS('All Features'!$B$2:$B$423,$B6,'All Features'!$C$2:$C$423,$C6,'All Features'!$O$2:$O$423,"COMPLETED") -> 27 | I6: =COUNTIFS('All Features'!$B$2:$B$423,$B6,'All Features'!$C$2:$C$423,$C6,'All Features'!$O$2:$O$423,"IMPLEMENTED BUT NOT VERIFIED") -> 4 | J6: =COUNTIFS('All Features'!$B$2:$B$423,$B6,'All Features'!$C$2:$C$423,$C6,'All Features'!$O$2:$O$423,"BLOCKED") -> 0 | K6: =COUNTIFS('All Features'!$B$2:$B$423,$B6,'All Features'!$C$2:$C$423,$C6,'All Features'!$O$2:$O$423,"IN PROGRESS") -> 0 | L6: =COUNTIFS('All Features'!$B$2:$B$423,$B6,'All Features'!$C$2:$C$423,$C6,'All Features'!$O$2:$O$423,"IN REVIEW*") -> 0 | M6: =COUNTIFS('All Features'!$B$2:$B$423,$B6,'All Features'!$C$2:$C$423,$C6,'All Features'!$O$2:$O$423,"NOT STARTED") -> 0 | N6: =COUNTIFS('All Features'!$B$2:$B$423,$B6,'All Features'!$C$2:$C$423,$C6,'All Features'!$O$2:$O$423,"SUPERSEDED") -> 0 | O6: =COUNTIFS('All Features'!$B$2:$B$423,$B6,'All Features'!$C$2:$C$423,$C6,'All Features'!$L$2:$L$423,"Yes") -> 31 | P6: =IFERROR((H6+N6)/G6,0) -> 0.87096774 | Q6: =IFERROR(AVERAGEIFS('All Features'!$Q$2:$Q$423,'All Features'!$B$2:$B$423,$B6,'All Features'!$C$2:$C$423,$C6),"") -> 0.83064516 | R6: =IF(G6=0,"-",IF(H6+N6=G6,"COMPLETED",IF(M6=G6,"NOT STARTED",IF(H6+I6+N6=G6,"BUILT - VERIFICATION PENDING","IN PROGRESS"&IF(J6>0," - "&J6&" BLOCKED","")&IF(L6>0," - "&L6&" in review",""))))) -> BUILT - VERIFICATION PENDING
A7: ATIP-DEV | B7: ATIP | C7: 2 | D7: Phase 2: Quant Research (data, factors, backtesting) | E7: =IF(COUNTIFS('All Features'!$B$2:$B$423,$B7,'All Features'!$C$2:$C$423,$C7,'All Features'!$J$2:$J$423,">0")=0,"",_xlfn.MINIFS('All Features'!$J$2:$J$423,'All Features'!$B$2:$B$423,$B7,'All Features'!$C$2:$C$423,$C7)) -> 46289 | F7: =IF(COUNTIFS('All Features'!$B$2:$B$423,$B7,'All Features'!$C$2:$C$423,$C7,'All Features'!$J$2:$J$423,">0")=0,"",_xlfn.MAXIFS('All Features'!$J$2:$J$423,'All Features'!$B$2:$B$423,$B7,'All Features'!$C$2:$C$423,$C7)) -> 46302 | G7: =COUNTIFS('All Features'!$B$2:$B$423,$B7,'All Features'!$C$2:$C$423,$C7) -> 52 | H7: =COUNTIFS('All Features'!$B$2:$B$423,$B7,'All Features'!$C$2:$C$423,$C7,'All Features'!$O$2:$O$423,"COMPLETED") -> 17 | I7: =COUNTIFS('All Features'!$B$2:$B$423,$B7,'All Features'!$C$2:$C$423,$C7,'All Features'!$O$2:$O$423,"IMPLEMENTED BUT NOT VERIFIED") -> 35 | J7: =COUNTIFS('All Features'!$B$2:$B$423,$B7,'All Features'!$C$2:$C$423,$C7,'All Features'!$O$2:$O$423,"BLOCKED") -> 0 | K7: =COUNTIFS('All Features'!$B$2:$B$423,$B7,'All Features'!$C$2:$C$423,$C7,'All Features'!$O$2:$O$423,"IN PROGRESS") -> 0 | L7: =COUNTIFS('All Features'!$B$2:$B$423,$B7,'All Features'!$C$2:$C$423,$C7,'All Features'!$O$2:$O$423,"IN REVIEW*") -> 0 | M7: =COUNTIFS('All Features'!$B$2:$B$423,$B7,'All Features'!$C$2:$C$423,$C7,'All Features'!$O$2:$O$423,"NOT STARTED") -> 0 | N7: =COUNTIFS('All Features'!$B$2:$B$423,$B7,'All Features'!$C$2:$C$423,$C7,'All Features'!$O$2:$O$423,"SUPERSEDED") -> 0 | O7: =COUNTIFS('All Features'!$B$2:$B$423,$B7,'All Features'!$C$2:$C$423,$C7,'All Features'!$L$2:$L$423,"Yes") -> 52 | P7: =IFERROR((H7+N7)/G7,0) -> 0.32692308 | Q7: =IFERROR(AVERAGEIFS('All Features'!$Q$2:$Q$423,'All Features'!$B$2:$B$423,$B7,'All Features'!$C$2:$C$423,$C7),"") -> 0.80673077 | R7: =IF(G7=0,"-",IF(H7+N7=G7,"COMPLETED",IF(M7=G7,"NOT STARTED",IF(H7+I7+N7=G7,"BUILT - VERIFICATION PENDING","IN PROGRESS"&IF(J7>0," - "&J7&" BLOCKED","")&IF(L7>0," - "&L7&" in review",""))))) -> BUILT - VERIFICATION PENDING
A8: ATIP-DEV | B8: ATIP | C8: 3 | D8: Phase 3: Strategy Engine | E8: =IF(COUNTIFS('All Features'!$B$2:$B$423,$B8,'All Features'!$C$2:$C$423,$C8,'All Features'!$J$2:$J$423,">0")=0,"",_xlfn.MINIFS('All Features'!$J$2:$J$423,'All Features'!$B$2:$B$423,$B8,'All Features'!$C$2:$C$423,$C8)) -> 46289 | F8: =IF(COUNTIFS('All Features'!$B$2:$B$423,$B8,'All Features'!$C$2:$C$423,$C8,'All Features'!$J$2:$J$423,">0")=0,"",_xlfn.MAXIFS('All Features'!$J$2:$J$423,'All Features'!$B$2:$B$423,$B8,'All Features'!$C$2:$C$423,$C8)) -> 46302 | G8: =COUNTIFS('All Features'!$B$2:$B$423,$B8,'All Features'!$C$2:$C$423,$C8) -> 14 | H8: =COUNTIFS('All Features'!$B$2:$B$423,$B8,'All Features'!$C$2:$C$423,$C8,'All Features'!$O$2:$O$423,"COMPLETED") -> 11 | I8: =COUNTIFS('All Features'!$B$2:$B$423,$B8,'All Features'!$C$2:$C$423,$C8,'All Features'!$O$2:$O$423,"IMPLEMENTED BUT NOT VERIFIED") -> 3 | J8: =COUNTIFS('All Features'!$B$2:$B$423,$B8,'All Features'!$C$2:$C$423,$C8,'All Features'!$O$2:$O$423,"BLOCKED") -> 0 | K8: =COUNTIFS('All Features'!$B$2:$B$423,$B8,'All Features'!$C$2:$C$423,$C8,'All Features'!$O$2:$O$423,"IN PROGRESS") -> 0 | L8: =COUNTIFS('All Features'!$B$2:$B$423,$B8,'All Features'!$C$2:$C$423,$C8,'All Features'!$O$2:$O$423,"IN REVIEW*") -> 0 | M8: =COUNTIFS('All Features'!$B$2:$B$423,$B8,'All Features'!$C$2:$C$423,$C8,'All Features'!$O$2:$O$423,"NOT STARTED") -> 0 | N8: =COUNTIFS('All Features'!$B$2:$B$423,$B8,'All Features'!$C$2:$C$423,$C8,'All Features'!$O$2:$O$423,"SUPERSEDED") -> 0 | O8: =COUNTIFS('All Features'!$B$2:$B$423,$B8,'All Features'!$C$2:$C$423,$C8,'All Features'!$L$2:$L$423,"Yes") -> 14 | P8: =IFERROR((H8+N8)/G8,0) -> 0.78571429 | Q8: =IFERROR(AVERAGEIFS('All Features'!$Q$2:$Q$423,'All Features'!$B$2:$B$423,$B8,'All Features'!$C$2:$C$423,$C8),"") -> 0.80357143 | R8: =IF(G8=0,"-",IF(H8+N8=G8,"COMPLETED",IF(M8=G8,"NOT STARTED",IF(H8+I8+N8=G8,"BUILT - VERIFICATION PENDING","IN PROGRESS"&IF(J8>0," - "&J8&" BLOCKED","")&IF(L8>0," - "&L8&" in review",""))))) -> BUILT - VERIFICATION PENDING
A9: ATIP-DEV | B9: ATIP | C9: 4 | D9: Phase 4: AI/ML | E9: =IF(COUNTIFS('All Features'!$B$2:$B$423,$B9,'All Features'!$C$2:$C$423,$C9,'All Features'!$J$2:$J$423,">0")=0,"",_xlfn.MINIFS('All Features'!$J$2:$J$423,'All Features'!$B$2:$B$423,$B9,'All Features'!$C$2:$C$423,$C9)) -> 46290 | F9: =IF(COUNTIFS('All Features'!$B$2:$B$423,$B9,'All Features'!$C$2:$C$423,$C9,'All Features'!$J$2:$J$423,">0")=0,"",_xlfn.MAXIFS('All Features'!$J$2:$J$423,'All Features'!$B$2:$B$423,$B9,'All Features'!$C$2:$C$423,$C9)) -> 46302 | G9: =COUNTIFS('All Features'!$B$2:$B$423,$B9,'All Features'!$C$2:$C$423,$C9) -> 21 | H9: =COUNTIFS('All Features'!$B$2:$B$423,$B9,'All Features'!$C$2:$C$423,$C9,'All Features'!$O$2:$O$423,"COMPLETED") -> 2 | I9: =COUNTIFS('All Features'!$B$2:$B$423,$B9,'All Features'!$C$2:$C$423,$C9,'All Features'!$O$2:$O$423,"IMPLEMENTED BUT NOT VERIFIED") -> 18 | J9: =COUNTIFS('All Features'!$B$2:$B$423,$B9,'All Features'!$C$2:$C$423,$C9,'All Features'!$O$2:$O$423,"BLOCKED") -> 1 | K9: =COUNTIFS('All Features'!$B$2:$B$423,$B9,'All Features'!$C$2:$C$423,$C9,'All Features'!$O$2:$O$423,"IN PROGRESS") -> 0 | L9: =COUNTIFS('All Features'!$B$2:$B$423,$B9,'All Features'!$C$2:$C$423,$C9,'All Features'!$O$2:$O$423,"IN REVIEW*") -> 0 | M9: =COUNTIFS('All Features'!$B$2:$B$423,$B9,'All Features'!$C$2:$C$423,$C9,'All Features'!$O$2:$O$423,"NOT STARTED") -> 0 | N9: =COUNTIFS('All Features'!$B$2:$B$423,$B9,'All Features'!$C$2:$C$423,$C9,'All Features'!$O$2:$O$423,"SUPERSEDED") -> 0 | O9: =COUNTIFS('All Features'!$B$2:$B$423,$B9,'All Features'!$C$2:$C$423,$C9,'All Features'!$L$2:$L$423,"Yes") -> 21 | P9: =IFERROR((H9+N9)/G9,0) -> 0.095238095 | Q9: =IFERROR(AVERAGEIFS('All Features'!$Q$2:$Q$423,'All Features'!$B$2:$B$423,$B9,'All Features'!$C$2:$C$423,$C9),"") -> 0.79761905 | R9: =IF(G9=0,"-",IF(H9+N9=G9,"COMPLETED",IF(M9=G9,"NOT STARTED",IF(H9+I9+N9=G9,"BUILT - VERIFICATION PENDING","IN PROGRESS"&IF(J9>0," - "&J9&" BLOCKED","")&IF(L9>0," - "&L9&" in review",""))))) -> IN PROGRESS - 1 BLOCKED
A10: ATIP-DEV | B10: ATIP | C10: 5 | D10: Phase 5: Risk & Portfolio | E10: =IF(COUNTIFS('All Features'!$B$2:$B$423,$B10,'All Features'!$C$2:$C$423,$C10,'All Features'!$J$2:$J$423,">0")=0,"",_xlfn.MINIFS('All Features'!$J$2:$J$423,'All Features'!$B$2:$B$423,$B10,'All Features'!$C$2:$C$423,$C10)) -> 46289 | F10: =IF(COUNTIFS('All Features'!$B$2:$B$423,$B10,'All Features'!$C$2:$C$423,$C10,'All Features'!$J$2:$J$423,">0")=0,"",_xlfn.MAXIFS('All Features'!$J$2:$J$423,'All Features'!$B$2:$B$423,$B10,'All Features'!$C$2:$C$423,$C10)) -> 46302 | G10: =COUNTIFS('All Features'!$B$2:$B$423,$B10,'All Features'!$C$2:$C$423,$C10) -> 17 | H10: =COUNTIFS('All Features'!$B$2:$B$423,$B10,'All Features'!$C$2:$C$423,$C10,'All Features'!$O$2:$O$423,"COMPLETED") -> 3 | I10: =COUNTIFS('All Features'!$B$2:$B$423,$B10,'All Features'!$C$2:$C$423,$C10,'All Features'!$O$2:$O$423,"IMPLEMENTED BUT NOT VERIFIED") -> 14 | J10: =COUNTIFS('All Features'!$B$2:$B$423,$B10,'All Features'!$C$2:$C$423,$C10,'All Features'!$O$2:$O$423,"BLOCKED") -> 0 | K10: =COUNTIFS('All Features'!$B$2:$B$423,$B10,'All Features'!$C$2:$C$423,$C10,'All Features'!$O$2:$O$423,"IN PROGRESS") -> 0 | L10: =COUNTIFS('All Features'!$B$2:$B$423,$B10,'All Features'!$C$2:$C$423,$C10,'All Features'!$O$2:$O$423,"IN REVIEW*") -> 0 | M10: =COUNTIFS('All Features'!$B$2:$B$423,$B10,'All Features'!$C$2:$C$423,$C10,'All Features'!$O$2:$O$423,"NOT STARTED") -> 0 | N10: =COUNTIFS('All Features'!$B$2:$B$423,$B10,'All Features'!$C$2:$C$423,$C10,'All Features'!$O$2:$O$423,"SUPERSEDED") -> 0 | O10: =COUNTIFS('All Features'!$B$2:$B$423,$B10,'All Features'!$C$2:$C$423,$C10,'All Features'!$L$2:$L$423,"Yes") -> 17 | P10: =IFERROR((H10+N10)/G10,0) -> 0.17647059 | Q10: =IFERROR(AVERAGEIFS('All Features'!$Q$2:$Q$423,'All Features'!$B$2:$B$423,$B10,'All Features'!$C$2:$C$423,$C10),"") -> 0.83529412 | R10: =IF(G10=0,"-",IF(H10+N10=G10,"COMPLETED",IF(M10=G10,"NOT STARTED",IF(H10+I10+N10=G10,"BUILT - VERIFICATION PENDING","IN PROGRESS"&IF(J10>0," - "&J10&" BLOCKED","")&IF(L10>0," - "&L10&" in review",""))))) -> BUILT - VERIFICATION PENDING
A11: ATIP-DEV | B11: ATIP | C11: 6 | D11: Phase 6: Execution | E11: =IF(COUNTIFS('All Features'!$B$2:$B$423,$B11,'All Features'!$C$2:$C$423,$C11,'All Features'!$J$2:$J$423,">0")=0,"",_xlfn.MINIFS('All Features'!$J$2:$J$423,'All Features'!$B$2:$B$423,$B11,'All Features'!$C$2:$C$423,$C11)) -> 46296 | F11: =IF(COUNTIFS('All Features'!$B$2:$B$423,$B11,'All Features'!$C$2:$C$423,$C11,'All Features'!$J$2:$J$423,">0")=0,"",_xlfn.MAXIFS('All Features'!$J$2:$J$423,'All Features'!$B$2:$B$423,$B11,'All Features'!$C$2:$C$423,$C11)) -> 46302 | G11: =COUNTIFS('All Features'!$B$2:$B$423,$B11,'All Features'!$C$2:$C$423,$C11) -> 11 | H11: =COUNTIFS('All Features'!$B$2:$B$423,$B11,'All Features'!$C$2:$C$423,$C11,'All Features'!$O$2:$O$423,"COMPLETED") -> 0 | I11: =COUNTIFS('All Features'!$B$2:$B$423,$B11,'All Features'!$C$2:$C$423,$C11,'All Features'!$O$2:$O$423,"IMPLEMENTED BUT NOT VERIFIED") -> 10 | J11: =COUNTIFS('All Features'!$B$2:$B$423,$B11,'All Features'!$C$2:$C$423,$C11,'All Features'!$O$2:$O$423,"BLOCKED") -> 1 | K11: =COUNTIFS('All Features'!$B$2:$B$423,$B11,'All Features'!$C$2:$C$423,$C11,'All Features'!$O$2:$O$423,"IN PROGRESS") -> 0 | L11: =COUNTIFS('All Features'!$B$2:$B$423,$B11,'All Features'!$C$2:$C$423,$C11,'All Features'!$O$2:$O$423,"IN REVIEW*") -> 0 | M11: =COUNTIFS('All Features'!$B$2:$B$423,$B11,'All Features'!$C$2:$C$423,$C11,'All Features'!$O$2:$O$423,"NOT STARTED") -> 0 | N11: =COUNTIFS('All Features'!$B$2:$B$423,$B11,'All Features'!$C$2:$C$423,$C11,'All Features'!$O$2:$O$423,"SUPERSEDED") -> 0 | O11: =COUNTIFS('All Features'!$B$2:$B$423,$B11,'All Features'!$C$2:$C$423,$C11,'All Features'!$L$2:$L$423,"Yes") -> 11 | P11: =IFERROR((H11+N11)/G11,0) -> 0 | Q11: =IFERROR(AVERAGEIFS('All Features'!$Q$2:$Q$423,'All Features'!$B$2:$B$423,$B11,'All Features'!$C$2:$C$423,$C11),"") -> 0.83636364 | R11: =IF(G11=0,"-",IF(H11+N11=G11,"COMPLETED",IF(M11=G11,"NOT STARTED",IF(H11+I11+N11=G11,"BUILT - VERIFICATION PENDING","IN PROGRESS"&IF(J11>0," - "&J11&" BLOCKED","")&IF(L11>0," - "&L11&" in review",""))))) -> IN PROGRESS - 1 BLOCKED
A12: ATIP-DEV | B12: ATIP | C12: 7 | D12: Phase 7: Advanced Quant | E12: =IF(COUNTIFS('All Features'!$B$2:$B$423,$B12,'All Features'!$C$2:$C$423,$C12,'All Features'!$J$2:$J$423,">0")=0,"",_xlfn.MINIFS('All Features'!$J$2:$J$423,'All Features'!$B$2:$B$423,$B12,'All Features'!$C$2:$C$423,$C12)) -> 46296 | F12: =IF(COUNTIFS('All Features'!$B$2:$B$423,$B12,'All Features'!$C$2:$C$423,$C12,'All Features'!$J$2:$J$423,">0")=0,"",_xlfn.MAXIFS('All Features'!$J$2:$J$423,'All Features'!$B$2:$B$423,$B12,'All Features'!$C$2:$C$423,$C12)) -> 46302 | G12: =COUNTIFS('All Features'!$B$2:$B$423,$B12,'All Features'!$C$2:$C$423,$C12) -> 19 | H12: =COUNTIFS('All Features'!$B$2:$B$423,$B12,'All Features'!$C$2:$C$423,$C12,'All Features'!$O$2:$O$423,"COMPLETED") -> 0 | I12: =COUNTIFS('All Features'!$B$2:$B$423,$B12,'All Features'!$C$2:$C$423,$C12,'All Features'!$O$2:$O$423,"IMPLEMENTED BUT NOT VERIFIED") -> 19 | J12: =COUNTIFS('All Features'!$B$2:$B$423,$B12,'All Features'!$C$2:$C$423,$C12,'All Features'!$O$2:$O$423,"BLOCKED") -> 0 | K12: =COUNTIFS('All Features'!$B$2:$B$423,$B12,'All Features'!$C$2:$C$423,$C12,'All Features'!$O$2:$O$423,"IN PROGRESS") -> 0 | L12: =COUNTIFS('All Features'!$B$2:$B$423,$B12,'All Features'!$C$2:$C$423,$C12,'All Features'!$O$2:$O$423,"IN REVIEW*") -> 0 | M12: =COUNTIFS('All Features'!$B$2:$B$423,$B12,'All Features'!$C$2:$C$423,$C12,'All Features'!$O$2:$O$423,"NOT STARTED") -> 0 | N12: =COUNTIFS('All Features'!$B$2:$B$423,$B12,'All Features'!$C$2:$C$423,$C12,'All Features'!$O$2:$O$423,"SUPERSEDED") -> 0 | O12: =COUNTIFS('All Features'!$B$2:$B$423,$B12,'All Features'!$C$2:$C$423,$C12,'All Features'!$L$2:$L$423,"Yes") -> 19 | P12: =IFERROR((H12+N12)/G12,0) -> 0 | Q12: =IFERROR(AVERAGEIFS('All Features'!$Q$2:$Q$423,'All Features'!$B$2:$B$423,$B12,'All Features'!$C$2:$C$423,$C12),"") -> 0.78684211 | R12: =IF(G12=0,"-",IF(H12+N12=G12,"COMPLETED",IF(M12=G12,"NOT STARTED",IF(H12+I12+N12=G12,"BUILT - VERIFICATION PENDING","IN PROGRESS"&IF(J12>0," - "&J12&" BLOCKED","")&IF(L12>0," - "&L12&" in review",""))))) -> BUILT - VERIFICATION PENDING
A13: ATIP-DEV | B13: ATIP | C13: 8 | D13: Phase 8: Production hardening | E13: =IF(COUNTIFS('All Features'!$B$2:$B$423,$B13,'All Features'!$C$2:$C$423,$C13,'All Features'!$J$2:$J$423,">0")=0,"",_xlfn.MINIFS('All Features'!$J$2:$J$423,'All Features'!$B$2:$B$423,$B13,'All Features'!$C$2:$C$423,$C13)) -> 46290 | F13: =IF(COUNTIFS('All Features'!$B$2:$B$423,$B13,'All Features'!$C$2:$C$423,$C13,'All Features'!$J$2:$J$423,">0")=0,"",_xlfn.MAXIFS('All Features'!$J$2:$J$423,'All Features'!$B$2:$B$423,$B13,'All Features'!$C$2:$C$423,$C13)) -> 46302 | G13: =COUNTIFS('All Features'!$B$2:$B$423,$B13,'All Features'!$C$2:$C$423,$C13) -> 14 | H13: =COUNTIFS('All Features'!$B$2:$B$423,$B13,'All Features'!$C$2:$C$423,$C13,'All Features'!$O$2:$O$423,"COMPLETED") -> 6 | I13: =COUNTIFS('All Features'!$B$2:$B$423,$B13,'All Features'!$C$2:$C$423,$C13,'All Features'!$O$2:$O$423,"IMPLEMENTED BUT NOT VERIFIED") -> 8 | J13: =COUNTIFS('All Features'!$B$2:$B$423,$B13,'All Features'!$C$2:$C$423,$C13,'All Features'!$O$2:$O$423,"BLOCKED") -> 0 | K13: =COUNTIFS('All Features'!$B$2:$B$423,$B13,'All Features'!$C$2:$C$423,$C13,'All Features'!$O$2:$O$423,"IN PROGRESS") -> 0 | L13: =COUNTIFS('All Features'!$B$2:$B$423,$B13,'All Features'!$C$2:$C$423,$C13,'All Features'!$O$2:$O$423,"IN REVIEW*") -> 0 | M13: =COUNTIFS('All Features'!$B$2:$B$423,$B13,'All Features'!$C$2:$C$423,$C13,'All Features'!$O$2:$O$423,"NOT STARTED") -> 0 | N13: =COUNTIFS('All Features'!$B$2:$B$423,$B13,'All Features'!$C$2:$C$423,$C13,'All Features'!$O$2:$O$423,"SUPERSEDED") -> 0 | O13: =COUNTIFS('All Features'!$B$2:$B$423,$B13,'All Features'!$C$2:$C$423,$C13,'All Features'!$L$2:$L$423,"Yes") -> 14 | P13: =IFERROR((H13+N13)/G13,0) -> 0.42857143 | Q13: =IFERROR(AVERAGEIFS('All Features'!$Q$2:$Q$423,'All Features'!$B$2:$B$423,$B13,'All Features'!$C$2:$C$423,$C13),"") -> 0.84642857 | R13: =IF(G13=0,"-",IF(H13+N13=G13,"COMPLETED",IF(M13=G13,"NOT STARTED",IF(H13+I13+N13=G13,"BUILT - VERIFICATION PENDING","IN PROGRESS"&IF(J13>0," - "&J13&" BLOCKED","")&IF(L13>0," - "&L13&" in review",""))))) -> BUILT - VERIFICATION PENDING
A14: ATIP-DEV | B14: ATIP | C14: 9 | D14: Phase 9: Enterprise SaaS (final objective) | E14: =IF(COUNTIFS('All Features'!$B$2:$B$423,$B14,'All Features'!$C$2:$C$423,$C14,'All Features'!$J$2:$J$423,">0")=0,"",_xlfn.MINIFS('All Features'!$J$2:$J$423,'All Features'!$B$2:$B$423,$B14,'All Features'!$C$2:$C$423,$C14)) -> 46290 | F14: =IF(COUNTIFS('All Features'!$B$2:$B$423,$B14,'All Features'!$C$2:$C$423,$C14,'All Features'!$J$2:$J$423,">0")=0,"",_xlfn.MAXIFS('All Features'!$J$2:$J$423,'All Features'!$B$2:$B$423,$B14,'All Features'!$C$2:$C$423,$C14)) -> 46302 | G14: =COUNTIFS('All Features'!$B$2:$B$423,$B14,'All Features'!$C$2:$C$423,$C14) -> 29 | H14: =COUNTIFS('All Features'!$B$2:$B$423,$B14,'All Features'!$C$2:$C$423,$C14,'All Features'!$O$2:$O$423,"COMPLETED") -> 2 | I14: =COUNTIFS('All Features'!$B$2:$B$423,$B14,'All Features'!$C$2:$C$423,$C14,'All Features'!$O$2:$O$423,"IMPLEMENTED BUT NOT VERIFIED") -> 22 | J14: =COUNTIFS('All Features'!$B$2:$B$423,$B14,'All Features'!$C$2:$C$423,$C14,'All Features'!$O$2:$O$423,"BLOCKED") -> 5 | K14: =COUNTIFS('All Features'!$B$2:$B$423,$B14,'All Features'!$C$2:$C$423,$C14,'All Features'!$O$2:$O$423,"IN PROGRESS") -> 0 | L14: =COUNTIFS('All Features'!$B$2:$B$423,$B14,'All Features'!$C$2:$C$423,$C14,'All Features'!$O$2:$O$423,"IN REVIEW*") -> 0 | M14: =COUNTIFS('All Features'!$B$2:$B$423,$B14,'All Features'!$C$2:$C$423,$C14,'All Features'!$O$2:$O$423,"NOT STARTED") -> 0 | N14: =COUNTIFS('All Features'!$B$2:$B$423,$B14,'All Features'!$C$2:$C$423,$C14,'All Features'!$O$2:$O$423,"SUPERSEDED") -> 0 | O14: =COUNTIFS('All Features'!$B$2:$B$423,$B14,'All Features'!$C$2:$C$423,$C14,'All Features'!$L$2:$L$423,"Yes") -> 29 | P14: =IFERROR((H14+N14)/G14,0) -> 0.068965517 | Q14: =IFERROR(AVERAGEIFS('All Features'!$Q$2:$Q$423,'All Features'!$B$2:$B$423,$B14,'All Features'!$C$2:$C$423,$C14),"") -> 0.7362069 | R14: =IF(G14=0,"-",IF(H14+N14=G14,"COMPLETED",IF(M14=G14,"NOT STARTED",IF(H14+I14+N14=G14,"BUILT - VERIFICATION PENDING","IN PROGRESS"&IF(J14>0," - "&J14&" BLOCKED","")&IF(L14>0," - "&L14&" in review",""))))) -> IN PROGRESS - 5 BLOCKED
A15: ATIP-DEV | B15: ATIP | C15: 10 | D15: Phase 10: Wealth track (Waves 11-20) | E15: =IF(COUNTIFS('All Features'!$B$2:$B$423,$B15,'All Features'!$C$2:$C$423,$C15,'All Features'!$J$2:$J$423,">0")=0,"",_xlfn.MINIFS('All Features'!$J$2:$J$423,'All Features'!$B$2:$B$423,$B15,'All Features'!$C$2:$C$423,$C15)) -> 46291 | F15: =IF(COUNTIFS('All Features'!$B$2:$B$423,$B15,'All Features'!$C$2:$C$423,$C15,'All Features'!$J$2:$J$423,">0")=0,"",_xlfn.MAXIFS('All Features'!$J$2:$J$423,'All Features'!$B$2:$B$423,$B15,'All Features'!$C$2:$C$423,$C15)) -> 46302 | G15: =COUNTIFS('All Features'!$B$2:$B$423,$B15,'All Features'!$C$2:$C$423,$C15) -> 11 | H15: =COUNTIFS('All Features'!$B$2:$B$423,$B15,'All Features'!$C$2:$C$423,$C15,'All Features'!$O$2:$O$423,"COMPLETED") -> 0 | I15: =COUNTIFS('All Features'!$B$2:$B$423,$B15,'All Features'!$C$2:$C$423,$C15,'All Features'!$O$2:$O$423,"IMPLEMENTED BUT NOT VERIFIED") -> 9 | J15: =COUNTIFS('All Features'!$B$2:$B$423,$B15,'All Features'!$C$2:$C$423,$C15,'All Features'!$O$2:$O$423,"BLOCKED") -> 1 | K15: =COUNTIFS('All Features'!$B$2:$B$423,$B15,'All Features'!$C$2:$C$423,$C15,'All Features'!$O$2:$O$423,"IN PROGRESS") -> 1 | L15: =COUNTIFS('All Features'!$B$2:$B$423,$B15,'All Features'!$C$2:$C$423,$C15,'All Features'!$O$2:$O$423,"IN REVIEW*") -> 0 | M15: =COUNTIFS('All Features'!$B$2:$B$423,$B15,'All Features'!$C$2:$C$423,$C15,'All Features'!$O$2:$O$423,"NOT STARTED") -> 0 | N15: =COUNTIFS('All Features'!$B$2:$B$423,$B15,'All Features'!$C$2:$C$423,$C15,'All Features'!$O$2:$O$423,"SUPERSEDED") -> 0 | O15: =COUNTIFS('All Features'!$B$2:$B$423,$B15,'All Features'!$C$2:$C$423,$C15,'All Features'!$L$2:$L$423,"Yes") -> 11 | P15: =IFERROR((H15+N15)/G15,0) -> 0 | Q15: =IFERROR(AVERAGEIFS('All Features'!$Q$2:$Q$423,'All Features'!$B$2:$B$423,$B15,'All Features'!$C$2:$C$423,$C15),"") -> 0.80454545 | R15: =IF(G15=0,"-",IF(H15+N15=G15,"COMPLETED",IF(M15=G15,"NOT STARTED",IF(H15+I15+N15=G15,"BUILT - VERIFICATION PENDING","IN PROGRESS"&IF(J15>0," - "&J15&" BLOCKED","")&IF(L15>0," - "&L15&" in review",""))))) -> IN PROGRESS - 1 BLOCKED
A16: ATIP-DEV | B16: ATIP | C16: 11 | D16: Phase 11: W39 reconciliation (owner tracker 2026-10-07) | E16: =IF(COUNTIFS('All Features'!$B$2:$B$423,$B16,'All Features'!$C$2:$C$423,$C16,'All Features'!$J$2:$J$423,">0")=0,"",_xlfn.MINIFS('All Features'!$J$2:$J$423,'All Features'!$B$2:$B$423,$B16,'All Features'!$C$2:$C$423,$C16)) -> 46302 | F16: =IF(COUNTIFS('All Features'!$B$2:$B$423,$B16,'All Features'!$C$2:$C$423,$C16,'All Features'!$J$2:$J$423,">0")=0,"",_xlfn.MAXIFS('All Features'!$J$2:$J$423,'All Features'!$B$2:$B$423,$B16,'All Features'!$C$2:$C$423,$C16)) -> 46302 | G16: =COUNTIFS('All Features'!$B$2:$B$423,$B16,'All Features'!$C$2:$C$423,$C16) -> 54 | H16: =COUNTIFS('All Features'!$B$2:$B$423,$B16,'All Features'!$C$2:$C$423,$C16,'All Features'!$O$2:$O$423,"COMPLETED") -> 0 | I16: =COUNTIFS('All Features'!$B$2:$B$423,$B16,'All Features'!$C$2:$C$423,$C16,'All Features'!$O$2:$O$423,"IMPLEMENTED BUT NOT VERIFIED") -> 53 | J16: =COUNTIFS('All Features'!$B$2:$B$423,$B16,'All Features'!$C$2:$C$423,$C16,'All Features'!$O$2:$O$423,"BLOCKED") -> 1 | K16: =COUNTIFS('All Features'!$B$2:$B$423,$B16,'All Features'!$C$2:$C$423,$C16,'All Features'!$O$2:$O$423,"IN PROGRESS") -> 0 | L16: =COUNTIFS('All Features'!$B$2:$B$423,$B16,'All Features'!$C$2:$C$423,$C16,'All Features'!$O$2:$O$423,"IN REVIEW*") -> 0 | M16: =COUNTIFS('All Features'!$B$2:$B$423,$B16,'All Features'!$C$2:$C$423,$C16,'All Features'!$O$2:$O$423,"NOT STARTED") -> 0 | N16: =COUNTIFS('All Features'!$B$2:$B$423,$B16,'All Features'!$C$2:$C$423,$C16,'All Features'!$O$2:$O$423,"SUPERSEDED") -> 0 | O16: =COUNTIFS('All Features'!$B$2:$B$423,$B16,'All Features'!$C$2:$C$423,$C16,'All Features'!$L$2:$L$423,"Yes") -> 54 | P16: =IFERROR((H16+N16)/G16,0) -> 0 | Q16: =IFERROR(AVERAGEIFS('All Features'!$Q$2:$Q$423,'All Features'!$B$2:$B$423,$B16,'All Features'!$C$2:$C$423,$C16),"") -> 0.84722222 | R16: =IF(G16=0,"-",IF(H16+N16=G16,"COMPLETED",IF(M16=G16,"NOT STARTED",IF(H16+I16+N16=G16,"BUILT - VERIFICATION PENDING","IN PROGRESS"&IF(J16>0," - "&J16&" BLOCKED","")&IF(L16>0," - "&L16&" in review",""))))) -> IN PROGRESS - 1 BLOCKED
... A37: bkesari-platform | B37: Education | C37: 10 | D37: Phase 10: Multilingual (on hold for translators) | E37: =IF(COUNTIFS('All Features'!$B$2:$B$423,$B37,'All Features'!$C$2:$C$423,$C37,'All Features'!$J$2:$J$423,">0")=0,"",_xlfn.MINIFS('All Features'!$J$2:$J$423,'All Features'!$B$2:$B$423,$B37,'All Features'!$C$2:$C$423,$C37)) | F37: =IF(COUNTIFS('All Features'!$B$2:$B$423,$B37,'All Features'!$C$2:$C$423,$C37,'All Features'!$J$2:$J$423,">0")=0,"",_xlfn.MAXIFS('All Features'!$J$2:$J$423,'All Features'!$B$2:$B$423,$B37,'All Features'!$C$2:$C$423,$C37)) | G37: =COUNTIFS('All Features'!$B$2:$B$423,$B37,'All Features'!$C$2:$C$423,$C37) -> 1 | H37: =COUNTIFS('All Features'!$B$2:$B$423,$B37,'All Features'!$C$2:$C$423,$C37,'All Features'!$O$2:$O$423,"COMPLETED") -> 0 | I37: =COUNTIFS('All Features'!$B$2:$B$423,$B37,'All Features'!$C$2:$C$423,$C37,'All Features'!$O$2:$O$423,"IMPLEMENTED BUT NOT VERIFIED") -> 0 | J37: =COUNTIFS('All Features'!$B$2:$B$423,$B37,'All Features'!$C$2:$C$423,$C37,'All Features'!$O$2:$O$423,"BLOCKED") -> 0 | K37: =COUNTIFS('All Features'!$B$2:$B$423,$B37,'All Features'!$C$2:$C$423,$C37,'All Features'!$O$2:$O$423,"IN PROGRESS") -> 0 | L37: =COUNTIFS('All Features'!$B$2:$B$423,$B37,'All Features'!$C$2:$C$423,$C37,'All Features'!$O$2:$O$423,"IN REVIEW*") -> 0 | M37: =COUNTIFS('All Features'!$B$2:$B$423,$B37,'All Features'!$C$2:$C$423,$C37,'All Features'!$O$2:$O$423,"NOT STARTED") -> 1 | N37: =COUNTIFS('All Features'!$B$2:$B$423,$B37,'All Features'!$C$2:$C$423,$C37,'All Features'!$O$2:$O$423,"SUPERSEDED") -> 0 | O37: =COUNTIFS('All Features'!$B$2:$B$423,$B37,'All Features'!$C$2:$C$423,$C37,'All Features'!$L$2:$L$423,"Yes") -> 0 | P37: =IFERROR((H37+N37)/G37,0) -> 0 | Q37: =IFERROR(AVERAGEIFS('All Features'!$Q$2:$Q$423,'All Features'!$B$2:$B$423,$B37,'All Features'!$C$2:$C$423,$C37),"") -> 0 | R37: =IF(G37=0,"-",IF(H37+N37=G37,"COMPLETED",IF(M37=G37,"NOT STARTED",IF(H37+I37+N37=G37,"BUILT - VERIFICATION PENDING","IN PROGRESS"&IF(J37>0," - "&J37&" BLOCKED","")&IF(L37>0," - "&L37&" in review",""))))) -> NOT STARTED
A39: Totals per app
A40: Repo | B40: App | C40: Phases | G40: Features | H40: Completed | I40: Implemented, not verified | J40: Blocked | K40: In progress | L40: In review (PR open) | M40: Not started | N40: Superseded | O40: On GitHub default branch | P40: % completed | Q40: Avg completion % (where recorded)
A41: ATIP-DEV | B41: ATIP | C41: =COUNTIFS($B$5:$B$37,$B41) -> 13 | G41: =SUMIFS(G$5:G$37,$B$5:$B$37,$B41) -> 337 | H41: =SUMIFS(H$5:H$37,$B$5:$B$37,$B41) -> 130 | I41: =SUMIFS(I$5:I$37,$B$5:$B$37,$B41) -> 197 | J41: =SUMIFS(J$5:J$37,$B$5:$B$37,$B41) -> 9 | K41: =SUMIFS(K$5:K$37,$B$5:$B$37,$B41) -> 1 | L41: =SUMIFS(L$5:L$37,$B$5:$B$37,$B41) -> 0 | M41: =SUMIFS(M$5:M$37,$B$5:$B$37,$B41) -> 0 | N41: =SUMIFS(N$5:N$37,$B$5:$B$37,$B41) -> 0 | O41: =SUMIFS(O$5:O$37,$B$5:$B$37,$B41) -> 337 | P41: =IFERROR((H41+N41)/G41,0) -> 0.38575668 | Q41: =IFERROR(AVERAGEIFS('All Features'!$Q$2:$Q$423,'All Features'!$B$2:$B$423,$B41),"") -> 0.81197605
A42: bkesari | B42: Milk & Dairy marketplace | C42: =COUNTIFS($B$5:$B$37,$B42) -> 6 | G42: =SUMIFS(G$5:G$37,$B$5:$B$37,$B42) -> 33 | H42: =SUMIFS(H$5:H$37,$B$5:$B$37,$B42) -> 32 | I42: =SUMIFS(I$5:I$37,$B$5:$B$37,$B42) -> 0 | J42: =SUMIFS(J$5:J$37,$B$5:$B$37,$B42) -> 0 | K42: =SUMIFS(K$5:K$37,$B$5:$B$37,$B42) -> 0 | L42: =SUMIFS(L$5:L$37,$B$5:$B$37,$B42) -> 1 | M42: =SUMIFS(M$5:M$37,$B$5:$B$37,$B42) -> 0 | N42: =SUMIFS(N$5:N$37,$B$5:$B$37,$B42) -> 0 | O42: =SUMIFS(O$5:O$37,$B$5:$B$37,$B42) -> 32 | P42: =IFERROR((H42+N42)/G42,0) -> 0.96969697 | Q42: =IFERROR(AVERAGEIFS('All Features'!$Q$2:$Q$423,'All Features'!$B$2:$B$423,$B42),"") -> 1
A43: bkesari-platform | B43: Portal (bkesari.com hub) | C43: =COUNTIFS($B$5:$B$37,$B43) -> 4 | G43: =SUMIFS(G$5:G$37,$B$5:$B$37,$B43) -> 21 | H43: =SUMIFS(H$5:H$37,$B$5:$B$37,$B43) -> 19 | I43: =SUMIFS(I$5:I$37,$B$5:$B$37,$B43) -> 0 | J43: =SUMIFS(J$5:J$37,$B$5:$B$37,$B43) -> 0 | K43: =SUMIFS(K$5:K$37,$B$5:$B$37,$B43) -> 0 | L43: =SUMIFS(L$5:L$37,$B$5:$B$37,$B43) -> 1 | M43: =SUMIFS(M$5:M$37,$B$5:$B$37,$B43) -> 0 | N43: =SUMIFS(N$5:N$37,$B$5:$B$37,$B43) -> 1 | O43: =SUMIFS(O$5:O$37,$B$5:$B$37,$B43) -> 20 | P43: =IFERROR((H43+N43)/G43,0) -> 0.95238095 | Q43: =IFERROR(AVERAGEIFS('All Features'!$Q$2:$Q$423,'All Features'!$B$2:$B$423,$B43),"") -> 1
A44: bkesari-platform | B44: Education | C44: =COUNTIFS($B$5:$B$37,$B44) -> 10 | G44: =SUMIFS(G$5:G$37,$B$5:$B$37,$B44) -> 31 | H44: =SUMIFS(H$5:H$37,$B$5:$B$37,$B44) -> 19 | I44: =SUMIFS(I$5:I$37,$B$5:$B$37,$B44) -> 0 | J44: =SUMIFS(J$5:J$37,$B$5:$B$37,$B44) -> 0 | K44: =SUMIFS(K$5:K$37,$B$5:$B$37,$B44) -> 0 | L44: =SUMIFS(L$5:L$37,$B$5:$B$37,$B44) -> 0 | M44: =SUMIFS(M$5:M$37,$B$5:$B$37,$B44) -> 12 | N44: =SUMIFS(N$5:N$37,$B$5:$B$37,$B44) -> 0 | O44: =SUMIFS(O$5:O$37,$B$5:$B$37,$B44) -> 19 | P44: =IFERROR((H44+N44)/G44,0) -> 0.61290323 | Q44: =IFERROR(AVERAGEIFS('All Features'!$Q$2:$Q$423,'All Features'!$B$2:$B$423,$B44),"") -> 0.61290323
B45: ALL | G45: =SUM(G41:G44) -> 422 | H45: =SUM(H41:H44) -> 200 | I45: =SUM(I41:I44) -> 197 | J45: =SUM(J41:J44) -> 9 | K45: =SUM(K41:K44) -> 1 | L45: =SUM(L41:L44) -> 2 | M45: =SUM(M41:M44) -> 12 | N45: =SUM(N41:N44) -> 1 | O45: =SUM(O41:O44) -> 408 | P45: =IFERROR((H45+N45)/G45,0) -> 0.47630332
B46: Check: phase totals match 'All Features' | G46: =IF(AND(G45=COUNTA('All Features'!$F$2:$F$423),SUM(H45:N45)=G45),"OK","MISMATCH") -> OK

Sheet All Features
A1: Repo | B1: App | C1: Phase # | D1: Phase | E1: Area | F1: Feature ID | G1: Feature | H1: Details | I1: Delivered by | J1: Date | K1: Branch | L1: On GitHub default branch? | M1: GitHub status | N1: Local Git (fresh clone) | O1: Status | P1: Testing status | Q1: Completion % | R1: Blocker / next action | S1: Link
A2: ATIP-DEV | B2: ATIP | C2: 0 | D2: Phase 0: Delivered baseline (maintain) | E2: Data Platform | F2: DP-02 | G2: Daily OHLCV history | H2: NSE Bhavcopy + Dhan; coverage/freshness/duplicate guards | I2: Tracker wave 2 | J2: 46289 | K2: master | L2: Yes | M2: Merged to master | N2: In local master | O2: COMPLETED | P2: IN PROGRESS | Q2: 0.9 | R2: Maintain | S2: https://github.com/sanjaymorankar-debug/ATIP-DEV/blob/master/docs/ATIP_MASTER_TRACKER.csv
A3: ATIP-DEV | B3: ATIP | C3: 0 | D3: Phase 0: Delivered baseline (maintain) | E3: Data Platform | F3: DP-07 | G3: Delivery data | H3: Full Bhavcopy nightly + backfill | I3: Tracker wave 2 | J3: 46289 | K3: master | L3: Yes | M3: Merged to master | N3: In local master | O3: COMPLETED | P3: COMPLETED | Q3: 0.9 | R3: Maintain | S3: https://github.com/sanjaymorankar-debug/ATIP-DEV/blob/master/docs/ATIP_MASTER_TRACKER.csv
A4: ATIP-DEV | B4: ATIP | C4: 0 | D4: Phase 0: Delivered baseline (maintain) | E4: Data Platform | F4: DP-20 | G4: Trading calendar | H4: 2025-26 holidays + budget sessions | I4: Tracker wave 2 | J4: 46289 | K4: master | L4: Yes | M4: Merged to master | N4: In local master | O4: COMPLETED | P4: COMPLETED | Q4: 0.9 | R4: Add next year's holidays each December | S4: https://github.com/sanjaymorankar-debug/ATIP-DEV/blob/master/docs/ATIP_MASTER_TRACKER.csv
A5: ATIP-DEV | B5: ATIP | C5: 0 | D5: Phase 0: Delivered baseline (maintain) | E5: Technical Analysis | F5: TA-01 | G5: Core indicators | H5: Computed and stored; MACD fixed and normalised | I5: Tracker wave 3 | J5: 46289 | K5: master | L5: Yes | M5: Merged to master | N5: In local master | O5: COMPLETED | P5: COMPLETED | Q5: 0.9 | R5: Maintain | S5: https://github.com/sanjaymorankar-debug/ATIP-DEV/blob/master/docs/ATIP_MASTER_TRACKER.csv
A6: ATIP-DEV | B6: ATIP | C6: 0 | D6: Phase 0: Delivered baseline (maintain) | E6: Technical Analysis | F6: TA-02 | G6: Extended oscillators | H6: Computed and stored | I6: Tracker wave 3 | J6: 46289 | K6: master | L6: Yes | M6: Merged to master | N6: In local master | O6: COMPLETED | P6: COMPLETED | Q6: 0.8 | R6: Maintain | S6: https://github.com/sanjaymorankar-debug/ATIP-DEV/blob/master/docs/ATIP_MASTER_TRACKER.csv
A7: ATIP-DEV | B7: ATIP | C7: 0 | D7: Phase 0: Delivered baseline (maintain) | E7: Technical Analysis | F7: TA-05 | G7: Fibonacci | H7: 52-week 23.6/38.2/50/61.8 levels; W39: swing-anchored Fibonacci (last two 5-bar pivots in 120 sessions, 38.2 / 50 / 61.8 levels, nearest level and distance) in technical_ext, shown in the stock panel | I7: Tracker wave 3 | J7: 46302 | K7: master | L7: Yes | M7: Merged to master | N7: In local master | O7: COMPLETED | P7: COMPLETED | Q7: 0.8 | R7: Independent QA | S7: https://github.com/sanjaymorankar-debug/ATIP-DEV/blob/master/docs/ATIP_MASTER_TRACKER.csv
A8: ATIP-DEV | B8: ATIP | C8: 0 | D8: Phase 0: Delivered baseline (maintain) | E8: Technical Analysis | F8: TA-07 | G8: Trend features | H8: Computed and stored | I8: Tracker wave 3 | J8: 46289 | K8: master | L8: Yes | M8: Merged to master | N8: In local master | O8: COMPLETED | P8: COMPLETED | Q8: 0.8 | R8: Maintain | S8: https://github.com/sanjaymorankar-debug/ATIP-DEV/blob/master/docs/ATIP_MASTER_TRACKER.csv
A9: ATIP-DEV | B9: ATIP | C9: 0 | D9: Phase 0: Delivered baseline (maintain) | E9: Technical Analysis | F9: TA-08 | G9: Relative strength | H9: 20-day RS with date-matched benchmark; W39 (TA-08b): 63 / 126-session RS vs the stock's sector index (NSE industry -> NIFTYIT / PHARMA / AUTO / FMCG / METAL / REALTY / ENERGY / BANK / PSUBANK, NIFTY50 fallback flagged) and percentile within the industry; display only | I9: Tracker wave 3 | J9: 46302 | K9: master | L9: Yes | M9: Merged to master | N9: In local master | O9: COMPLETED | P9: COMPLETED | Q9: 0.8 | R9: Independent QA; IC research before any score use | S9: https://github.com/sanjaymorankar-debug/ATIP-DEV/blob/master/docs/ATIP_MASTER_TRACKER.csv
A10: ATIP-DEV | B10: ATIP | C10: 0 | D10: Phase 0: Delivered baseline (maintain) | E10: Alpha/Factor Engine | F10: SC-03 | G10: RRI | H10: Implemented | I10: Tracker wave 4 | J10: 46289 | K10: master | L10: Yes | M10: Merged to master | N10: In local master | O10: COMPLETED | P10: COMPLETED | Q10: 0.75 | R10: Institutional input improves with SC-14 | S10: https://github.com/sanjaymorankar-debug/ATIP-DEV/blob/master/docs/ATIP_MASTER_TRACKER.csv
A11: ATIP-DEV | B11: ATIP | C11: 0 | D11: Phase 0: Delivered baseline (maintain) | E11: Alpha/Factor Engine | F11: SC-04 | G11: MRI | H11: Implemented; MACD corrected | I11: Tracker wave 4 | J11: 46289 | K11: master | L11: Yes | M11: Merged to master | N11: In local master | O11: COMPLETED | P11: COMPLETED | Q11: 0.85 | R11: Maintain | S11: https://github.com/sanjaymorankar-debug/ATIP-DEV/blob/master/docs/ATIP_MASTER_TRACKER.csv
A12: ATIP-DEV | B12: ATIP | C12: 0 | D12: Phase 0: Delivered baseline (maintain) | E12: Alpha/Factor Engine | F12: SC-07 | G12: ZPI | H12: Implemented + delivery component | I12: Tracker wave 4 | J12: 46289 | K12: master | L12: Yes | M12: Merged to master | N12: In local master | O12: COMPLETED | P12: COMPLETED | Q12: 0.8 | R12: Maintain | S12: https://github.com/sanjaymorankar-debug/ATIP-DEV/blob/master/docs/ATIP_MASTER_TRACKER.csv
A13: ATIP-DEV | B13: ATIP | C13: 0 | D13: Phase 0: Delivered baseline (maintain) | E13: Alpha/Factor Engine | F13: SC-10 | G13: Portfolio Health score | H13: Implemented | I13: Tracker wave 4 | J13: 46289 | K13: master | L13: Yes | M13: Merged to master | N13: In local master | O13: COMPLETED | P13: IN PROGRESS | Q13: 0.75 | R13: Correlation/drawdown inputs come with PF-09 and PF-13 | S13: https://github.com/sanjaymorankar-debug/ATIP-DEV/blob/master/docs/ATIP_MASTER_TRACKER.csv
... A332: ATIP-DEV | B332: ATIP | C332: 11 | D332: Phase 11: W39 reconciliation (owner tracker 2026-10-07) | E332: Wealth / Mutual funds | F332: W39B-MFA | G332: Mutual fund analytics on stored AMFI NAVs (read-only) | H332: data/mf_analytics.py: point-to-point and CAGR returns, 1Y / 3Y rolling returns with hurdle stats, volatility / Sharpe / Sortino, drawdown with dates, beta / alpha / tracking error vs a price index, SIP and lump-sum XIRR, category rank among stored schemes, side-by-side compare; 3 read-only GET routes; scheme detail card on /data-platform | I332: W39b (PR #5) | J332: 46302 | K332: master | L332: Yes | M332: Merged to master | N332: In local master | O332: IMPLEMENTED BUT NOT VERIFIED | P332: COMPLETED | Q332: 0.85 | R332: Independent QA. Holding MFs in the wealth ledger stays out of scope (owner Scope Exclusions); benchmark is a price index, not total return; peers limited to stored schemes | S332: https://github.com/sanjaymorankar-debug/ATIP-DEV/blob/master/docs/ATIP_MASTER_TRACKER.csv
A333: ATIP-DEV | B333: ATIP | C333: 12 | D333: Phase 12: Platform: macOS and MySQL / PostgreSQL (PRs #1-#8) | E333: Database (MySQL) | F333: PR8-MYSQL | G333: MySQL runtime switch | H333: Translates the SQL constructs MySQL rejects (CAST, derived tables, self-reference), quotes MySQL-reserved column names (a test now keeps it at zero), fixes the two upserts that broke, pins the MySQL session time zone. SQLite stays the default; MySQL stays behind allow_experimental. | I333: PR #8 | J333: 46303 | K333: claude/awesome-dijkstra-fmccpl | L333: Yes | M333: Merged to master | N333: In local master | O333: COMPLETED | P333: PASS - full suite 1,336 passed (CI green) | R333: - | S333: https://github.com/sanjaymorankar-debug/ATIP-DEV/pull/8
A334: ATIP-DEV | B334: ATIP | C334: 12 | D334: Phase 12: Platform: macOS and MySQL / PostgreSQL (PRs #1-#8) | E334: macOS | F334: PF-1 | G334: Run ATIP on macOS | H334: start_atip.sh, LaunchAgents for the platform, the 5-minute snapshot upload and the daily Dhan token refresh; paths resolved from the script's own location | I334: PR #1 | J334: 46298 | K334: master | L334: Yes | M334: Merged to master | N334: In local master | O334: IMPLEMENTED BUT NOT VERIFIED | P334: PASS - full suite 1,336 passed (CI green) | R334: Owner check on the Mac | S334: https://github.com/sanjaymorankar-debug/ATIP-DEV/pull/1
A335: ATIP-DEV | B335: ATIP | C335: 12 | D335: Phase 12: Platform: macOS and MySQL / PostgreSQL (PRs #1-#8) | E335: Database | F335: PF-1 | G335: MySQL and PostgreSQL backends, data migration, serving at /ATIP/ | H335: db.mysql / db.postgres translation layers, tools/sqlite_to_mysql.py and sqlite_to_postgres.py, ATIP_ROOT_PATH for serving under /ATIP/ | I335: PR #1, #3 | J335: 46302 | K335: master | L335: Yes | M335: Merged to master | N335: In local master | O335: IMPLEMENTED BUT NOT VERIFIED | P335: PASS - full suite 1,336 passed (CI green) | R335: Owner check on the Mac | S335: https://github.com/sanjaymorankar-debug/ATIP-DEV/pull/1
A336: ATIP-DEV | B336: ATIP | C336: 12 | D336: Phase 12: Platform: macOS and MySQL / PostgreSQL (PRs #1-#8) | E336: Database | F336: PF-2 | G336: Schema scripts for a fresh database | H336: db/sql: SQLite, PostgreSQL and MySQL scripts generated from db.schema, verified against real servers | I336: PR #2 | J336: 46298 | K336: master | L336: Yes | M336: Merged to master | N336: In local master | O336: COMPLETED | P336: PASS - full suite 1,336 passed (CI green) | Q336: 1 | R336: - | S336: https://github.com/sanjaymorankar-debug/ATIP-DEV/pull/2
A337: ATIP-DEV | B337: ATIP | C337: 12 | D337: Phase 12: Platform: macOS and MySQL / PostgreSQL (PRs #1-#8) | E337: Database | F337: PF-6 | G337: --init reports the database it built | H337: main.py --init names the backend and database it actually created instead of always a SQLite path | I337: PR #6 | J337: 46302 | K337: master | L337: Yes | M337: Merged to master | N337: In local master | O337: COMPLETED | P337: PASS - full suite 1,336 passed (CI green) | Q337: 1 | R337: - | S337: https://github.com/sanjaymorankar-debug/ATIP-DEV/pull/6
A338: ATIP-DEV | B338: ATIP | C338: 12 | D338: Phase 12: Platform: macOS and MySQL / PostgreSQL (PRs #1-#8) | E338: Docs | F338: PF-7 | G338: Mac setup notes in the README | H338: Python 3.11+ from Homebrew, .env for the API key, Documents privacy, iCloud, sleep and time-zone checks | I338: PR #7 | J338: 46302 | K338: master | L338: Yes | M338: Merged to master | N338: In local master | O338: COMPLETED | P338: PASS - full suite 1,336 passed (CI green) | Q338: 1 | R338: - | S338: https://github.com/sanjaymorankar-debug/ATIP-DEV/pull/7
A339: bkesari | B339: Milk & Dairy marketplace | C339: 1 | D339: Phase 1: Core marketplace (19 Aug, PRs #1-#5) | E339: Website | F339: BK-01 | G339: Landing page and custom domain | H339: Placeholder landing page and CNAME for bkesari.com | I339: PR #2, #3 | J339: 46253 | K339: main | L339: Yes | M339: Merged to main | N339: In local main | O339: COMPLETED | P339: No dedicated test | Q339: 1 | R339: - | S339: https://github.com/sanjaymorankar-debug/bkesari/pull/2
A340: bkesari | B340: Milk & Dairy marketplace | C340: 1 | D340: Phase 1: Core marketplace (19 Aug, PRs #1-#5) | E340: Platform | F340: BK-02 | G340: Marketplace app foundation | H340: Next.js 16, React 19, TypeScript, Tailwind v4, Drizzle ORM (PostgreSQL at first, MySQL since PR #9), Auth.js (Google OAuth; email-only sign-in in development) | I340: PR #4 | J340: 46253 | K340: main | L340: Yes | M340: Merged to main | N340: In local main | O340: COMPLETED | P340: PASS - Automated tests: authorization.test.ts, acceptance.spec.ts (E2E) | Q340: 1 | R340: - | S340: https://github.com/sanjaymorankar-debug/bkesari/pull/4
A341: bkesari | B341: Milk & Dairy marketplace | C341: 1 | D341: Phase 1: Core marketplace (19 Aug, PRs #1-#5) | E341: Catalogue | F341: BK-03 | G341: Catalogue and shop browsing | H341: Home, Dairy, Bakery, Shops, shop page, search; seed with 5 demo shops, 18 categories, 40 products | I341: PR #4 | J341: 46253 | K341: main | L341: Yes | M341: Merged to main | N341: In local main | O341: COMPLETED | P341: PASS - Automated tests: acceptance.spec.ts (E2E) | Q341: 1 | R341: - | S341: https://github.com/sanjaymorankar-debug/bkesari/pull/4
A342: bkesari | B342: Milk & Dairy marketplace | C342: 1 | D342: Phase 1: Core marketplace (19 Aug, PRs #1-#5) | E342: Catalogue | F342: BK-04 | G342: Online / offline product control | H342: A product is purchasable online only if shop APPROVED, offering active, online enabled, online price set and stock suffices; enforced server-side and by DB CHECK constraints | I342: PR #4 | J342: 46253 | K342: main | L342: Yes | M342: Merged to main | N342: In local main | O342: COMPLETED | P342: PASS - Automated tests: checkout.test.ts | Q342: 1 | R342: - | S342: https://github.com/sanjaymorankar-debug/bkesari/pull/4
A343: bkesari | B343: Milk & Dairy marketplace | C343: 1 | D343: Phase 1: Core marketplace (19 Aug, PRs #1-#5) | E343: Shops | F343: BK-05 | G343: Kesari / Green shop classification | H343: Operator/admin-only classification; shop owners cannot change their own; every change audited | I343: PR #4 | J343: 46253 | K343: main | L343: Yes | M343: Merged to main | N343: In local main | O343: COMPLETED | P343: PASS - Automated tests: authorization.test.ts | Q343: 1 | R343: - | S343: https://github.com/sanjaymorankar-debug/bkesari/pull/4
A344: bkesari | B344: Milk & Dairy marketplace | C344: 1 | D344: Phase 1: Core marketplace (19 Aug, PRs #1-#5) | E344: Orders | F344: BK-06 | G344: Cart and checkout | H344: Server-validated cart, checkout from wallet, order lines snapshot name and price | I344: PR #4 | J344: 46253 | K344: main | L344: Yes | M344: Merged to main | N344: In local main | O344: COMPLETED | P344: PASS - Automated tests: checkout.test.ts | Q344: 1 | R344: - | S344: https://github.com/sanjaymorankar-debug/bkesari/pull/4
A345: bkesari | B345: Milk & Dairy marketplace | C345: 1 | D345: Phase 1: Core marketplace (19 Aug, PRs #1-#5) | E345: Wallet | F345: BK-07 | G345: Wallet with append-only ledger | H345: Integer paise, concurrency-safe debits, overdraw impossible, replay-safe operations, self-verifying ledger | I345: PR #4 | J345: 46253 | K345: main | L345: Yes | M345: Merged to main | N345: In local main | O345: COMPLETED | P345: PASS - Automated tests: wallet.test.ts | Q345: 1 | R345: - | S345: https://github.com/sanjaymorankar-debug/bkesari/pull/4
A346: bkesari | B346: Milk & Dairy marketplace | C346: 1 | D346: Phase 1: Core marketplace (19 Aug, PRs #1-#5) | E346: Subscriptions | F346: BK-08 | G346: Daily subscription engine | H346: Weekly schedule, pause, skip, per-date override, retry after top-up, calendar; idempotent daily-order cron (/api/cron/daily-orders) | I346: PR #4 | J346: 46253 | K346: main | L346: Yes | M346: Merged to main | N346: In local main | O346: COMPLETED | P346: PASS - Automated tests: subscription-engine.test.ts, schedule.test.ts | Q346: 1 | R346: Schedule the cron once daily on the host (DEPLOYMENT.md section 5) | S346: https://github.com/sanjaymorankar-debug/bkesari/pull/4
A347: bkesari | B347: Milk & Dairy marketplace | C347: 1 | D347: Phase 1: Core marketplace (19 Aug, PRs #1-#5) | E347: Admin | F347: BK-09 | G347: Shop registration, approval and dashboards | H347: Shop registration, operator approve/reject, operator and admin dashboards, notifications, audit log of sensitive mutations | I347: PR #4 | J347: 46253 | K347: main | L347: Yes | M347: Merged to main | N347: In local main | O347: COMPLETED | P347: PASS - Automated tests: authorization.test.ts | Q347: 1 | R347: - | S347: https://github.com/sanjaymorankar-debug/bkesari/pull/4
... A370: bkesari | B370: Milk & Dairy marketplace | C370: 6 | D370: Phase 6: MySQL and the bkesari.com hub (8-9 Oct, PRs #9, #10, #12, #13) | E370: Admin | F370: BK-32 | G370: Admin dashboard works on MySQL; migrate reads DB_* settings | H370: Two PostgreSQL ::bigint casts left in src/app/admin/page.tsx made /admin answer 500 on MySQL; db:migrate now builds its URL from DB_* like the app; README brought to MySQL. Opened by another session | I370: PR #12 | J370: 46303 | K370: claude/charming-edison-ofoncf | L370: Yes | M370: Merged to main | N370: In local main | O370: COMPLETED | P370: PASS - 284/284 on MySQL, also with a .env copied from .env.example (CI green) | Q370: 1 | R370: - | S370: https://github.com/sanjaymorankar-debug/bkesari/pull/12
A371: bkesari | B371: Milk & Dairy marketplace | C371: 6 | D371: Phase 6: MySQL and the bkesari.com hub (8-9 Oct, PRs #9, #10, #12, #13) | E371: Testing | F371: BK-33 | G371: Test database gets its own migrate command | H371: npm run db:migrate:test applies the schema to TEST_DATABASE_URL from .env, instead of a bash-only DATABASE_URL=... prefix. Opened by another session on 2026-10-09 | I371: PR #14 | J371: 46303 | K371: claude/awesome-dijkstra-fmccpl | L371: No | M371: Open PR - not merged | N371: Only on branch claude/awesome-dijkstra-fmccpl | O371: IN REVIEW (open PR) | P371: Its author reports 284/284 on MySQL 8.0; not re-run here | R371: Review, then merge or close PR #14 | S371: https://github.com/sanjaymorankar-debug/bkesari/pull/14
A372: bkesari-platform | B372: Portal (bkesari.com hub) | C372: 1 | D372: Phase 1: Portal and Task Tracker (16 Sep) | E372: Portal | F372: PL-01 | G372: Welcome portal with site menu | H372: bkesari.com landing page; menu picks test or production links from the address it is opened on | I372: commits 8f5356b, f88b45e | J372: 46281 | K372: main | L372: Yes | M372: Merged to main | N372: In local main | O372: COMPLETED | P372: PASS - 44 tests + 32 guard checks; Task Tracker saves to MySQL | Q372: 1 | R372: - | S372: https://github.com/sanjaymorankar-debug/bkesari-platform/commit/8f5356b
A373: bkesari-platform | B373: Portal (bkesari.com hub) | C373: 1 | D373: Phase 1: Portal and Task Tracker (16 Sep) | E373: Portal | F373: PL-02 | G373: Task Tracker (/tasks/) | H373: Projects and tasks with owner, status, planned/actual dates, current/next step, timestamped status updates, dashboard counts, overdue flag, search and filter; login-protected | I373: commit 8f5356b | J373: 46281 | K373: main | L373: Yes | M373: Merged to main | N373: In local main | O373: COMPLETED | P373: PASS - 44 tests + 32 guard checks; Task Tracker saves to MySQL | Q373: 1 | R373: Set TRACKER_USER / TRACKER_PASSWORD | S373: https://github.com/sanjaymorankar-debug/bkesari-platform/commit/8f5356b
A374: bkesari-platform | B374: Portal (bkesari.com hub) | C374: 1 | D374: Phase 1: Portal and Task Tracker (16 Sep) | E374: Portal | F374: PL-03 | G374: ATIP read-only viewer (/atip/) | H374: Token-protected snapshot upload from your PC, login-protected viewer, order buttons hidden, CSP blocks all network calls | I374: commits 4e864ef, f88b45e | J374: 46281 | K374: main | L374: Yes | M374: Merged to main | N374: In local main | O374: COMPLETED | P374: PASS - 44 tests + 32 guard checks; Task Tracker saves to MySQL | Q374: 1 | R374: Set ATIP_USER / ATIP_PASSWORD / ATIP_PUBLISH_TOKEN | S374: https://github.com/sanjaymorankar-debug/bkesari-platform/commit/4e864ef
A375: bkesari-platform | B375: Portal (bkesari.com hub) | C375: 1 | D375: Phase 1: Portal and Task Tracker (16 Sep) | E375: Portal | F375: PL-04 | G375: MySQL / SQLite database adapter | H375: Same SQL on MySQL (Hostinger) and SQLite (local, node:sqlite, Node 22.13+) | I375: commit 8f5356b | J375: 46281 | K375: main | L375: Yes | M375: Merged to main | N375: In local main | O375: COMPLETED | P375: PASS - 44 tests + 32 guard checks; Task Tracker saves to MySQL | Q375: 1 | R375: - | S375: https://github.com/sanjaymorankar-debug/bkesari-platform/commit/8f5356b
A376: bkesari-platform | B376: Portal (bkesari.com hub) | C376: 1 | D376: Phase 1: Portal and Task Tracker (16 Sep) | E376: Monorepo | F376: PL-05 | G376: Combined repo: portal + edu + atip | H376: Portal (from bkesari-portal), Education (from edu, feature/spec-v2-build) and a copy of ATIP combined into one repo | I376: commits 69c012b..f88b45e | J376: 46281 | K376: main | L376: Yes | M376: Merged to main | N376: In local main | O376: COMPLETED | P376: No automated tests | Q376: 1 | R376: - | S376: https://github.com/sanjaymorankar-debug/bkesari-platform/commit/69c012b
A377: bkesari-platform | B377: Portal (bkesari.com hub) | C377: 1 | D377: Phase 1: Portal and Task Tracker (16 Sep) | E377: ATIP copy | F377: PL-06 | G377: Vendored ATIP snapshot in atip/ | H377: Copy of ATIP as of 2026-09-10. Removed by PR #1 on 2026-10-08; atip/ now only points to the ATIP-DEV repo | I377: commit 62b88a6 | J377: 46281 | K377: main | L377: Yes | M377: Merged to main | N377: In local main | O377: SUPERSEDED | P377: No automated tests | Q377: 1 | R377: Use ATIP-DEV | S377: https://github.com/sanjaymorankar-debug/bkesari-platform/commit/62b88a6
A378: bkesari-platform | B378: Portal (bkesari.com hub) | C378: 2 | D378: Phase 2: Database scripts and three tiers (1-2 Oct) | E378: Database | F378: PL-07 | G378: phpMyAdmin SQL deployment scripts | H378: Runnable SQL for edu (schema, reference, demo, first admin), ladwani and portal | I378: commit aeb7336 | J378: 46296 | K378: main | L378: Yes | M378: Merged to main | N378: In local main | O378: COMPLETED | P378: No automated tests | Q378: 1 | R378: - | S378: https://github.com/sanjaymorankar-debug/bkesari-platform/commit/aeb7336
A379: bkesari-platform | B379: Portal (bkesari.com hub) | C379: 2 | D379: Phase 2: Database scripts and three tiers (1-2 Oct) | E379: Database | F379: PL-08 | G379: Ladwani full-rebuild schema | H379: 69-table schema + reference data + first admin from the NestJS/Next.js rebuild | I379: commit 87fd505 | J379: 46296 | K379: main | L379: Yes | M379: Merged to main | N379: In local main | O379: COMPLETED | P379: No automated tests | Q379: 1 | R379: Regenerated by PR #1 (adds the missing M6) | S379: https://github.com/sanjaymorankar-debug/bkesari-platform/commit/87fd505
A380: bkesari-platform | B380: Portal (bkesari.com hub) | C380: 2 | D380: Phase 2: Database scripts and three tiers (1-2 Oct) | E380: Docs | F380: PL-09 | G380: Three-tier dev / test / production pipeline | H380: DEPLOY.md: dev -> staging -> main branches, one database per tier, hPanel steps | I380: commit f37140e | J380: 46297 | K380: main | L380: Yes | M380: Merged to main | N380: In local main | O380: COMPLETED | P380: No automated tests | Q380: 1 | R380: dev/test/prod sites must be created in hPanel | S380: https://github.com/sanjaymorankar-debug/bkesari-platform/commit/f37140e
A381: bkesari-platform | B381: Portal (bkesari.com hub) | C381: 3 | D381: Phase 3: The bkesari.com hub: dev tier, shared menu, app tabs, CI (8 Oct, PRs #1, #2) | E381: Portal | F381: PL-41 | G381: Dev tier and ATIP at /ATIP/ | H381: dev.bkesari.com tier; ATIP viewer moved to /ATIP/ | I381: PR #1 | J381: 46297 | K381: claude/awesome-dijkstra-fmccpl | L381: Yes | M381: Merged to main | N381: In local main | O381: COMPLETED | P381: PASS - portal 44 + 32 guard, edu 387/387 (CI green) | Q381: 1 | R381: - | S381: https://github.com/sanjaymorankar-debug/bkesari-platform/pull/1
A382: bkesari-platform | B382: Portal (bkesari.com hub) | C382: 3 | D382: Phase 3: The bkesari.com hub: dev tier, shared menu, app tabs, CI (8 Oct, PRs #1, #2) | E382: ATIP copy | F382: PL-42 | G382: Drop the stale vendored ATIP copy | H382: Deletes atip/ (ATIP-DEV is the source of truth) | I382: PR #1 | J382: 46297 | K382: claude/awesome-dijkstra-fmccpl | L382: Yes | M382: Merged to main | N382: In local main | O382: COMPLETED | P382: PASS - portal 44 + 32 guard, edu 387/387 (CI green) | Q382: 1 | R382: - | S382: https://github.com/sanjaymorankar-debug/bkesari-platform/pull/1
A383: bkesari-platform | B383: Portal (bkesari.com hub) | C383: 3 | D383: Phase 3: The bkesari.com hub: dev tier, shared menu, app tabs, CI (8 Oct, PRs #1, #2) | E383: Education (edu/) | F383: PL-43 | G383: edu macOS launcher | H383: Mac launcher for Education pointed at the bkesari tiers | I383: PR #1 | J383: 46297 | K383: claude/awesome-dijkstra-fmccpl | L383: Yes | M383: Merged to main | N383: In local main | O383: COMPLETED | P383: PASS - portal 44 + 32 guard, edu 387/387 (CI green) | Q383: 1 | R383: - | S383: https://github.com/sanjaymorankar-debug/bkesari-platform/pull/1
... A389: bkesari-platform | B389: Portal (bkesari.com hub) | C389: 3 | D389: Phase 3: The bkesari.com hub: dev tier, shared menu, app tabs, CI (8 Oct, PRs #1, #2) | E389: Portal | F389: PL-49 | G389: App tabs through the hub (/milk/, LadWani, /edu/) | H389: Each project served under its own tab path; Education at /edu/ via prefix stripping | I389: PR #2 | J389: 46303 | K389: claude/amazing-cannon-5n3fro | L389: Yes | M389: Merged to main | N389: In local main | O389: COMPLETED | P389: PASS - portal 44 + 32 guard, edu 387/387 (CI green) | Q389: 1 | R389: - | S389: https://github.com/sanjaymorankar-debug/bkesari-platform/pull/2
A390: bkesari-platform | B390: Portal (bkesari.com hub) | C390: 3 | D390: Phase 3: The bkesari.com hub: dev tier, shared menu, app tabs, CI (8 Oct, PRs #1, #2) | E390: Testing | F390: PL-50 | G390: Portal database tests on both MySQL and SQLite | H390: tests/db-dialects.test.js runs the same cases on both clients, a CI job runs them on MySQL 8.0, and the adapters gain close(). Opened by another session on 2026-10-09 | I390: PR #5 | J390: 46304 | K390: claude/awesome-dijkstra-fmccpl | L390: No | M390: Open PR - not merged | N390: Only on branch claude/awesome-dijkstra-fmccpl | O390: IN REVIEW (open PR) | P390: Its author reports 61 passed on MySQL 8.0 (53 + 8 skipped without it); not re-run here | R390: Review, then merge or close PR #5 | S390: https://github.com/sanjaymorankar-debug/bkesari-platform/pull/5
A391: bkesari-platform | B391: Portal (bkesari.com hub) | C391: 4 | D391: Phase 4: Mac setup and local tooling (8-9 Oct, PRs #3, #4) | E391: Docs | F391: PL-51 | G391: Mac setup guide, feature status workbook, local Git checker | H391: docs/MAC_DEPLOYMENT.md, this workbook, tools/check_local_git.sh | I391: PR #3 | J391: 46303 | K391: main | L391: Yes | M391: Merged to main | N391: In local main | O391: COMPLETED | P391: PASS - checker tested on a clone with unpushed, local-only and dirty state; workbook 0 formula errors | Q391: 1 | R391: - | S391: https://github.com/sanjaymorankar-debug/bkesari-platform/pull/3
A392: bkesari-platform | B392: Portal (bkesari.com hub) | C392: 4 | D392: Phase 4: Mac setup and local tooling (8-9 Oct, PRs #3, #4) | E392: Database | F392: PL-52 | G392: Local MySQL setup script | H392: tools/setup_local_mysql.sh: one database + user per site on the Mac's MySQL, writes each app's .env, runs migrations, seeds empty databases; safe to re-run | I392: PR #4 (arrived with this workbook) | J392: 46304 | K392: main | L392: Yes | M392: Merged to main | N392: In local main | O392: COMPLETED | P392: PASS - fresh run and re-run against MySQL 8.0; all three sites then served from it (CI green) | Q392: 1 | R392: Run it once on the Mac: tools/setup_local_mysql.sh | S392: https://github.com/sanjaymorankar-debug/bkesari-platform/pull/4
A393: bkesari-platform | B393: Education | C393: 1 | D393: Phase 1: Core vertical slice | E393: Education (edu/) | F393: PL-10 | G393: Phase 1 core: search, profiles, faceless complaints | H393: Auth + RBAC for 12 roles, public school search and profiles, teacher ratings, faceless (anonymised) complaints, resolution confirmation, audit + identity-access logs | I393: commit e33e4cc | J393: 46259 | K393: main | L393: Yes | M393: Merged to main | N393: In local main | O393: COMPLETED | P393: PASS - edu suite 387/387 | Q393: 1 | R393: - | S393: https://github.com/sanjaymorankar-debug/bkesari-platform/commit/e33e4cc
A394: bkesari-platform | B394: Education | C394: 2 | D394: Phase 2: Dashboards, admin panel, onboarding | E394: Education (edu/) | F394: PL-11 | G394: School registration and onboarding | H394: Public school registration (pending until officer verifies), parent/student/teacher onboarding with school-admin approval | I394: commit 1606f39 | J394: 46260 | K394: main | L394: Yes | M394: Merged to main | N394: In local main | O394: COMPLETED | P394: PASS - edu suite 387/387 | Q394: 1 | R394: - | S394: https://github.com/sanjaymorankar-debug/bkesari-platform/commit/1606f39
A395: bkesari-platform | B395: Education | C395: 2 | D395: Phase 2: Dashboards, admin panel, onboarding | E395: Education (edu/) | F395: PL-12 | G395: Phase 2: dashboards, admin panel, retaliation, TEI, AI-assist | H395: Role dashboards, admin panel, retaliation reporting, Teacher Effectiveness Index, School Quality Index, rule-based AI assist | I395: commit fe1a321 | J395: 46260 | K395: main | L395: Yes | M395: Merged to main | N395: In local main | O395: COMPLETED | P395: PASS - edu suite 387/387 | Q395: 1 | R395: - | S395: https://github.com/sanjaymorankar-debug/bkesari-platform/commit/fe1a321
A396: bkesari-platform | B396: Education | C396: 2 | D396: Phase 2: Dashboards, admin panel, onboarding | E396: Education (edu/) | F396: PL-13 | G396: Two-way parent/student registration | H396: Parent-with-child registration and school invites | I396: commit 5598b92 | J396: 46260 | K396: main | L396: Yes | M396: Merged to main | N396: In local main | O396: COMPLETED | P396: PASS - edu suite 387/387 | Q396: 1 | R396: - | S396: https://github.com/sanjaymorankar-debug/bkesari-platform/commit/5598b92
A397: bkesari-platform | B397: Education | C397: 2 | D397: Phase 2: Dashboards, admin panel, onboarding | E397: Education (edu/) | F397: PL-40 | G397: Age-appropriate design pass for the student dashboard | H397: The dashboard works but reuses the parent dashboard's design; the dedicated pass is not started (ROADMAP: partially built) | I397: edu/ROADMAP.md | K397: - | L397: No | M397: Not built | N397: Not built | O397: NOT STARTED | P397: N/A | Q397: 0 | R397: The dashboard works but reuses the parent dashboard's design; the dedicated pass is not started (ROADMAP: partially built) | S397: https://github.com/sanjaymorankar-debug/bkesari-platform/blob/main/edu/ROADMAP.md
A398: bkesari-platform | B398: Education | C398: 3 | D398: Phase 3: 2FA, appeals, notifications, analytics | E398: Education (edu/) | F398: PL-14 | G398: 2FA, appeals, notifications, analytics, fraud flags | H398: TOTP 2FA + recovery codes, appeals workflow, notifications bell, analytics snapshots, TEI value-add, fraud flagging, admin roles, mail delivery | I398: commit 7e2c9da | J398: 46260 | K398: main | L398: Yes | M398: Merged to main | N398: In local main | O398: COMPLETED | P398: PASS - edu suite 387/387 | Q398: 1 | R398: - | S398: https://github.com/sanjaymorankar-debug/bkesari-platform/commit/7e2c9da
A399: bkesari-platform | B399: Education | C399: 3 | D399: Phase 3: 2FA, appeals, notifications, analytics | E399: Education (edu/) | F399: PL-39 | G399: TEI classroom-observation and professional-development inputs | H399: No data source for either (ROADMAP: deferred entirely) | I399: edu/ROADMAP.md | K399: - | L399: No | M399: Not built | N399: Not built | O399: NOT STARTED | P399: N/A | Q399: 0 | R399: No data source for either (ROADMAP: deferred entirely) | S399: https://github.com/sanjaymorankar-debug/bkesari-platform/blob/main/edu/ROADMAP.md
A400: bkesari-platform | B400: Education | C400: 4 | D400: Phase 4: Student growth, career and life readiness | E400: Education (edu/) | F400: PL-15 | G400: Student growth, career and life readiness | H400: NEP 2020 / PARAKH-aligned growth records, growth plans, career interest, life skills, on a DPDP Act s.9 consent layer | I400: commit 37eb766 | J400: 46267 | K400: main | L400: Yes | M400: Merged to main | N400: In local main | O400: COMPLETED | P400: PASS - edu suite 387/387 | Q400: 1 | R400: - | S400: https://github.com/sanjaymorankar-debug/bkesari-platform/commit/37eb766
A401: bkesari-platform | B401: Education | C401: 4 | D401: Phase 4: Student growth, career and life readiness | E401: Education (edu/) | F401: PL-29 | G401: Peer observation UI | H401: Model and policy exist; no screen yet (deliberate) | I401: edu/ROADMAP.md | K401: - | L401: No | M401: Not built | N401: Not built | O401: NOT STARTED | P401: N/A | Q401: 0 | R401: Model and policy exist; no screen yet (deliberate) | S401: https://github.com/sanjaymorankar-debug/bkesari-platform/blob/main/edu/ROADMAP.md
A402: bkesari-platform | B402: Education | C402: 4 | D402: Phase 4: Student growth, career and life readiness | E402: Education (edu/) | F402: PL-30 | G402: Alumni outcomes (spec s.17) | H402: Needs its own opt-in consent flow | I402: edu/ROADMAP.md | K402: - | L402: No | M402: Not built | N402: Not built | O402: NOT STARTED | P402: N/A | Q402: 0 | R402: Needs its own opt-in consent flow | S402: https://github.com/sanjaymorankar-debug/bkesari-platform/blob/main/edu/ROADMAP.md
A403: bkesari-platform | B403: Education | C403: 4 | D403: Phase 4: Student growth, career and life readiness | E403: Education (edu/) | F403: PL-31 | G403: Aggregate government growth/career views (s.32) | H403: Must be anonymised aggregates | I403: edu/ROADMAP.md | K403: - | L403: No | M403: Not built | N403: Not built | O403: NOT STARTED | P403: N/A | Q403: 0 | R403: Must be anonymised aggregates | S403: https://github.com/sanjaymorankar-debug/bkesari-platform/blob/main/edu/ROADMAP.md
A404: bkesari-platform | B404: Education | C404: 4 | D404: Phase 4: Student growth, career and life readiness | E404: Education (edu/) | F404: PL-32 | G404: Bias review checkpoint before wide rollout (s.45) | H404: Human review + single-school pilot | I404: edu/ROADMAP.md | K404: - | L404: No | M404: Not built | N404: Not built | O404: NOT STARTED | P404: N/A | Q404: 0 | R404: Human review + single-school pilot | S404: https://github.com/sanjaymorankar-debug/bkesari-platform/blob/main/edu/ROADMAP.md
A405: bkesari-platform | B405: Education | C405: 5 | D405: Phase 5: School core: UDISE, fees, facilities | E405: Education (edu/) | F405: PL-16 | G405: UDISE and fee transparency | H405: UDISE code, per-year fee register, mid-year revisions with reason, first-year vs continuing cost | I405: commit 54cc817 | J405: 46268 | K405: main | L405: Yes | M405: Merged to main | N405: In local main | O405: COMPLETED | P405: PASS - edu suite 387/387 | Q405: 1 | R405: - | S405: https://github.com/sanjaymorankar-debug/bkesari-platform/commit/54cc817
A406: bkesari-platform | B406: Education | C406: 5 | D406: Phase 5: School core: UDISE, fees, facilities | E406: Education (edu/) | F406: PL-17 | G406: Facilities: claimed vs experienced | H406: Facility claims, anonymous ratings, reported difference with a 3-report floor | I406: commit 50ee343 | J406: 46268 | K406: main | L406: Yes | M406: Merged to main | N406: In local main | O406: COMPLETED | P406: PASS - edu suite 387/387 | Q406: 1 | R406: - | S406: https://github.com/sanjaymorankar-debug/bkesari-platform/commit/50ee343
A407: bkesari-platform | B407: Education | C407: 5 | D407: Phase 5: School core: UDISE, fees, facilities | E407: Education (edu/) | F407: PL-33 | G407: Evidence file uploads on facility claims | H407: Column exists; upload not wired | I407: edu/ROADMAP.md | K407: - | L407: No | M407: Not built | N407: Not built | O407: NOT STARTED | P407: N/A | Q407: 0 | R407: Column exists; upload not wired | S407: https://github.com/sanjaymorankar-debug/bkesari-platform/blob/main/edu/ROADMAP.md
A408: bkesari-platform | B408: Education | C408: 6 | D408: Phase 6: Safeguarding, exams and coaching, health | E408: Education (edu/) | F408: PL-18 | G408: Safeguarding and mandatory reporting | H408: Separate POCSO-aware workflow, hidden from school admins, cannot close without external report | I408: commit 22c5f7c | J408: 46268 | K408: main | L408: Yes | M408: Merged to main | N408: In local main | O408: COMPLETED | P408: PASS - edu suite 387/387 | Q408: 1 | R408: - | S408: https://github.com/sanjaymorankar-debug/bkesari-platform/commit/22c5f7c
A409: bkesari-platform | B409: Education | C409: 6 | D409: Phase 6: Safeguarding, exams and coaching, health | E409: Education (edu/) | F409: PL-19 | G409: External exams and coaching | H409: Closes spec Phase 1; compulsory programmes billed outside the fee register shown as extra cost | I409: commit f0b8b28 | J409: 46268 | K409: main | L409: Yes | M409: Merged to main | N409: In local main | O409: COMPLETED | P409: PASS - edu suite 387/387 | Q409: 1 | R409: - | S409: https://github.com/sanjaymorankar-debug/bkesari-platform/commit/f0b8b28
A410: bkesari-platform | B410: Education | C410: 6 | D410: Phase 6: Safeguarding, exams and coaching, health | E410: Education (edu/) | F410: PL-20 | G410: Health and wellbeing | H410: Consent-gated screenings with follow-up lifecycle, teacher observations, counsellor tier | I410: commit 37f8d0f | J410: 46268 | K410: main | L410: Yes | M410: Merged to main | N410: In local main | O410: COMPLETED | P410: PASS - edu suite 387/387 | Q410: 1 | R410: - | S410: https://github.com/sanjaymorankar-debug/bkesari-platform/commit/37f8d0f
A411: bkesari-platform | B411: Education | C411: 6 | D411: Phase 6: Safeguarding, exams and coaching, health | E411: Education (edu/) | F411: PL-28 | G411: DPDP data-subject requests and retention | H411: Data-subject requests, declared retention periods, DPO and career-mentor seed accounts | I411: commits 04195e0, 7e86c8d | J411: 46268 | K411: main | L411: Yes | M411: Merged to main | N411: In local main | O411: COMPLETED | P411: PASS - edu suite 387/387 | Q411: 1 | R411: - | S411: https://github.com/sanjaymorankar-debug/bkesari-platform/commit/04195e0
A412: bkesari-platform | B412: Education | C412: 6 | D412: Phase 6: Safeguarding, exams and coaching, health | E412: Education (edu/) | F412: PL-34 | G412: Document uploads on health records | H412: Needs malware scan + private storage | I412: edu/ROADMAP.md | K412: - | L412: No | M412: Not built | N412: Not built | O412: NOT STARTED | P412: N/A | Q412: 0 | R412: Needs malware scan + private storage | S412: https://github.com/sanjaymorankar-debug/bkesari-platform/blob/main/edu/ROADMAP.md
A413: bkesari-platform | B413: Education | C413: 6 | D413: Phase 6: Safeguarding, exams and coaching, health | E413: Education (edu/) | F413: PL-35 | G413: Retention enforcement job | H413: Periods declared; no automatic sweep yet; needs legal review | I413: edu/ROADMAP.md | K413: - | L413: No | M413: Not built | N413: Not built | O413: NOT STARTED | P413: N/A | Q413: 0 | R413: Periods declared; no automatic sweep yet; needs legal review | S413: https://github.com/sanjaymorankar-debug/bkesari-platform/blob/main/edu/ROADMAP.md
A414: bkesari-platform | B414: Education | C414: 7 | D414: Phase 7: International benchmarking, government aggregates | E414: Education (edu/) | F414: PL-21 | G414: International benchmarking (How India Compares) | H414: Structural comparison layer, no score table | I414: commit a1793dd | J414: 46268 | K414: main | L414: Yes | M414: Merged to main | N414: In local main | O414: COMPLETED | P414: PASS - edu suite 387/387 | Q414: 1 | R414: - | S414: https://github.com/sanjaymorankar-debug/bkesari-platform/commit/a1793dd
A415: bkesari-platform | B415: Education | C415: 7 | D415: Phase 7: International benchmarking, government aggregates | E415: Education (edu/) | F415: PL-22 | G415: Anonymised health aggregates for government | H415: Small-cell suppression; District/State/National dashboards | I415: commits 79b24ff, 89e0466 | J415: 46268 | K415: main | L415: Yes | M415: Merged to main | N415: In local main | O415: COMPLETED | P415: PASS - edu suite 387/387 | Q415: 1 | R415: - | S415: https://github.com/sanjaymorankar-debug/bkesari-platform/commit/79b24ff
A416: bkesari-platform | B416: Education | C416: 7 | D416: Phase 7: International benchmarking, government aggregates | E416: Education (edu/) | F416: PL-36 | G416: NAS data integration and real AI model for AI-assist | H416: No dataset wired; AI-assist is rule-based | I416: edu/ROADMAP.md | K416: - | L416: No | M416: Not built | N416: Not built | O416: NOT STARTED | P416: N/A | Q416: 0 | R416: No dataset wired; AI-assist is rule-based | S416: https://github.com/sanjaymorankar-debug/bkesari-platform/blob/main/edu/ROADMAP.md
A417: bkesari-platform | B417: Education | C417: 8 | D417: Phase 8: Accessibility | E417: Education (edu/) | F417: PL-24 | G417: WCAG 2.1 AA fixes | H417: Skip link, page titles, live announcements, rating-scale labels, focus states | I417: commit 7024cd6 | J417: 46268 | K417: main | L417: Yes | M417: Merged to main | N417: In local main | O417: COMPLETED | P417: PASS - edu suite 387/387 | Q417: 1 | R417: - | S417: https://github.com/sanjaymorankar-debug/bkesari-platform/commit/7024cd6
A418: bkesari-platform | B418: Education | C418: 8 | D418: Phase 8: Accessibility | E418: Education (edu/) | F418: PL-38 | G418: Full accessibility audit with assistive technology | H418: Only regression guards so far | I418: edu/ROADMAP.md | K418: - | L418: No | M418: Not built | N418: Not built | O418: NOT STARTED | P418: N/A | Q418: 0 | R418: Only regression guards so far | S418: https://github.com/sanjaymorankar-debug/bkesari-platform/blob/main/edu/ROADMAP.md
A419: bkesari-platform | B419: Education | C419: 9 | D419: Phase 9: Further spec modules (built after the roadmap phases) | E419: Education (edu/) | F419: PL-23 | G419: Course and curriculum ratings | H419: 10 curriculum dimensions with response counts | I419: commit 41789d7 | J419: 46268 | K419: main | L419: Yes | M419: Merged to main | N419: In local main | O419: COMPLETED | P419: PASS - edu suite 387/387 | Q419: 1 | R419: - | S419: https://github.com/sanjaymorankar-debug/bkesari-platform/commit/41789d7
A420: bkesari-platform | B420: Education | C420: 9 | D420: Phase 9: Further spec modules (built after the roadmap phases) | E420: Education (edu/) | F420: PL-25 | G420: School right of reply | H420: Schools can respond to reported discrepancies | I420: commit 084066e | J420: 46268 | K420: main | L420: Yes | M420: Merged to main | N420: In local main | O420: COMPLETED | P420: PASS - edu suite 387/387 | Q420: 1 | R420: - | S420: https://github.com/sanjaymorankar-debug/bkesari-platform/commit/084066e
A421: bkesari-platform | B421: Education | C421: 9 | D421: Phase 9: Further spec modules (built after the roadmap phases) | E421: Education (edu/) | F421: PL-26 | G421: School Improvement Dashboard | H421: Spec section 31 | I421: commit fe1cba1 | J421: 46268 | K421: main | L421: Yes | M421: Merged to main | N421: In local main | O421: COMPLETED | P421: PASS - edu suite 387/387 | Q421: 1 | R421: - | S421: https://github.com/sanjaymorankar-debug/bkesari-platform/commit/fe1cba1
A422: bkesari-platform | B422: Education | C422: 9 | D422: Phase 9: Further spec modules (built after the roadmap phases) | E422: Education (edu/) | F422: PL-27 | G422: Officer verification queue | H422: Queue for officers to verify schools and records | I422: commit 13cc956 | J422: 46268 | K422: main | L422: Yes | M422: Merged to main | N422: In local main | O422: COMPLETED | P422: PASS - edu suite 387/387 | Q422: 1 | R422: - | S422: https://github.com/sanjaymorankar-debug/bkesari-platform/commit/13cc956
A423: bkesari-platform | B423: Education | C423: 10 | D423: Phase 10: Multilingual (on hold for translators) | E423: Education (edu/) | F423: PL-37 | G423: Multilingual (12 languages) | H423: On hold pending professional translators | I423: edu/ROADMAP.md | K423: - | L423: No | M423: Not built | N423: Not built | O423: NOT STARTED | P423: N/A | Q423: 0 | R423: On hold pending professional translators | S423: https://github.com/sanjaymorankar-debug/bkesari-platform/blob/main/edu/ROADMAP.md

Sheet ATIP Waves
A1: Wave | B1: Scope | C1: Branch | D1: Merged to master? | E1: Merged on (commit date) | F1: Development status | G1: Deployment (as recorded in repo docs)
A2: W1 | B2: Foundation: job monitoring, alerts, P&L, loss limits, sizing, data quality | C2: w1-foundation | D2: Yes | E2: 2026-09-24 | F2: COMPLETED | G2: Deployed 2026-09-28 with release ATIP-W24-RC1 (per WAVE_STATUS.md)
A3: W2 | B3: Research / backtesting framework | C3: w2-backtesting | D3: Yes | E3: 2026-09-24 | F3: COMPLETED | G3: Deployed 2026-09-28 with release ATIP-W24-RC1 (per WAVE_STATUS.md)
A4: W3 | B4: Strategy engine | C4: w3-strategy-engine | D4: Yes | E4: 2026-09-25 | F4: IMPLEMENTED BUT NOT VERIFIED (independent QA pending) | G4: Deployed 2026-09-28 with release ATIP-W24-RC1 (per WAVE_STATUS.md)
A5: W4 | B5: Risk and execution (paper) | C5: w4-risk-execution | D5: Yes | E5: 2026-09-25 | F5: IMPLEMENTED BUT NOT VERIFIED (independent QA pending) | G5: Deployed 2026-09-28 with release ATIP-W24-RC1 (per WAVE_STATUS.md)
A6: W5 | B6: AI / ML | C6: w5-ai-ml | D6: Yes | E6: 2026-09-25 | F6: IMPLEMENTED BUT NOT VERIFIED (independent QA pending) | G6: Deployed 2026-09-28 with release ATIP-W24-RC1 (per WAVE_STATUS.md)
A7: W6 | B7: Advanced quant | C7: w6-advanced-quant | D7: Yes | E7: 2026-09-25 | F7: IMPLEMENTED BUT NOT VERIFIED (independent QA pending) | G7: Deployed 2026-09-28 with release ATIP-W24-RC1 (per WAVE_STATUS.md)
A8: W7 | B8: Enterprise: users, tenants, RBAC, billing foundation | C8: w7-enterprise | D8: Yes | E8: 2026-09-25 | F8: PARTIALLY COMPLETED (ENT-07 internet exposure blocked) | G8: Deployed 2026-09-28 with release ATIP-W24-RC1 (per WAVE_STATUS.md)
A9: W8 | B9: Production hardening: health, metrics, backups, migrations, MFA, audit chain | C9: w8-production-hardening | D9: Yes | E9: 2026-09-26 | F9: IMPLEMENTED BUT NOT VERIFIED (independent QA pending) | G9: Deployed 2026-09-26 (production restarted onto W8; per WAVE_STATUS.md)
A10: W9 | B10: Final release and deployment readiness (deploy / rollback scripts) | C10: w9-release | D10: Yes | E10: 2026-09-26 | F10: IMPLEMENTED BUT NOT VERIFIED (independent QA pending) | G10: Deployed 2026-09-28 with release ATIP-W24-RC1 (per WAVE_STATUS.md)
A11: W11 | B11: Investor DNA (ATIP-INV-001) | C11: w11-investor-dna | D11: Yes | E11: 2026-09-26 | F11: IMPLEMENTED BUT NOT VERIFIED (independent QA pending) | G11: Deployed 2026-09-28 with release ATIP-W24-RC1 (per WAVE_STATUS.md)
A12: W12 | B12: Multi-asset wealth dashboard (ATIP-WLT-001) | C12: w12-wealth-dashboard | D12: Yes | E12: 2026-09-26 | F12: IMPLEMENTED BUT NOT VERIFIED (independent QA pending) | G12: Deployed 2026-09-28 with release ATIP-W24-RC1 (per WAVE_STATUS.md)
... A46: MySQL runtime | B46: MySQL runtime translation, reserved-word quoting, session time zone (PR #8) | C46: claude/awesome-dijkstra-fmccpl | D46: Yes | E46: 2026-10-09 | F46: IMPLEMENTED BUT NOT VERIFIED (experimental; SQLite stays the default) | G46: In master; not switched on (database.backend stays sqlite)
A48: Source: docs/WAVE_STATUS.md and the W*_HANDOFF.md files in ATIP-DEV. 'Merged to master' and 'Merged on' are measured from git, which supersedes WAVE_STATUS.md's 'no (branch)' entries for W25-W38: those branches were merged after that table was written.

Sheet Pull Requests
A1: Repo | B1: PR # | C1: Title | D1: Head branch | E1: Base | F1: Status | G1: Opened (UTC) | H1: Merged (UTC) | I1: In local default branch? | J1: Link
A2: ATIP-DEV | B2: 8 | C2: MySQL runtime: translate what cannot translate, quote what MySQL reserves | D2: claude/awesome-dijkstra-fmccpl | E2: master | F2: Merged | G2: 2026-10-08 | H2: 2026-10-08 | I2: Yes | J2: https://github.com/sanjaymorankar-debug/ATIP-DEV/pull/8
A3: ATIP-DEV | B3: 7 | C3: Add the Mac setup notes the README was missing | D3: claude/adoring-mccarthy-uesz2i | E3: master | F3: Merged | G3: 2026-10-07 | H3: 2026-10-07 | I3: Yes | J3: https://github.com/sanjaymorankar-debug/ATIP-DEV/pull/7
A4: ATIP-DEV | B4: 6 | C4: Make --init report the database it actually built, not always a SQLite path | D4: claude/awesome-dijkstra-fmccpl | E4: master | F4: Merged | G4: 2026-10-07 | H4: 2026-10-07 | I4: Yes | J4: https://github.com/sanjaymorankar-debug/ATIP-DEV/pull/6
A5: ATIP-DEV | B5: 5 | C5: W39b: reconcile the owner's Wave 1-20 tracker and build the remaining features | D5: claude/wizardly-curie-fbjeoa | E5: master | F5: Merged | G5: 2026-10-07 | H5: 2026-10-08 | I5: Yes | J5: https://github.com/sanjaymorankar-debug/ATIP-DEV/pull/5
A6: ATIP-DEV | B6: 4 | C6: Dhan token auto-refresh on macOS; W39: history, research, stock screener, signals (market gate, track record, weekly rating, chart patterns), market pulse, options builder | D6: ccr-643d84fc-yig8ts | E6: master | F6: Merged | G6: 2026-10-07 | H6: 2026-10-08 | I6: Yes | J6: https://github.com/sanjaymorankar-debug/ATIP-DEV/pull/4
A7: ATIP-DEV | B7: 3 | C7: Correct db/sql claims that merging #1 made false | D7: claude/awesome-dijkstra-fmccpl | E7: master | F7: Merged | G7: 2026-10-03 | H7: 2026-10-07 | I7: Yes | J7: https://github.com/sanjaymorankar-debug/ATIP-DEV/pull/3
A8: ATIP-DEV | B8: 2 | C8: Add schema scripts for a fresh ATIP database (SQLite, PostgreSQL, MySQL) | D8: claude/jolly-fermat-pawy3o | E8: master | F8: Merged | G8: 2026-10-03 | H8: 2026-10-03 | I8: Yes | J8: https://github.com/sanjaymorankar-debug/ATIP-DEV/pull/2
A9: ATIP-DEV | B9: 1 | C9: Move ATIP to macOS, make MySQL and PostgreSQL actually work, add a data migration, and serve it at /ATIP/ | D9: claude/awesome-dijkstra-fmccpl | E9: master | F9: Merged | G9: 2026-10-02 | H9: 2026-10-03 | I9: Yes | J9: https://github.com/sanjaymorankar-debug/ATIP-DEV/pull/1
A10: bkesari | B10: 12 | C10: Fix the admin dashboard's 500, and make the documented local setup work | D10: claude/charming-edison-ofoncf | E10: main | F10: Merged | G10: 2026-10-08 | H10: 2026-10-09 | I10: Yes | J10: https://github.com/sanjaymorankar-debug/bkesari/pull/12
A11: bkesari | B11: 14 | C11: Give the test database a migrate command of its own | D11: claude/awesome-dijkstra-fmccpl | E11: main | F11: Open - not merged | G11: 2026-10-09 | H11: - | I11: No | J11: https://github.com/sanjaymorankar-debug/bkesari/pull/14
A12: bkesari | B12: 13 | C12: Fill blank test secrets too, so tests pass after cp .env.example .env | D12: claude/epic-brown-iurf1w | E12: main | F12: Merged | G12: 2026-10-08 | H12: 2026-10-09 | I12: Yes | J12: https://github.com/sanjaymorankar-debug/bkesari/pull/13
A13: bkesari | B13: 11 | C13: Move the permanent-admin list out of source into PERMANENT_ADMIN_EMAILS (SEC-03) | D13: claude/charming-edison-ofoncf | E13: main | F13: Merged | G13: 2026-10-02 | H13: 2026-10-02 | I13: Yes | J13: https://github.com/sanjaymorankar-debug/bkesari/pull/11
... A28: bkesari-platform | B28: 1 | C28: dev tier, ATIP at /ATIP/, drop the stale ATIP copy, and fix the Ladwani SQL | D28: claude/awesome-dijkstra-fmccpl | E28: main | F28: Merged | G28: 2026-10-02 | H28: 2026-10-08 | I28: Yes | J28: https://github.com/sanjaymorankar-debug/bkesari-platform/pull/1

Sheet Branches
A1: Repo | B1: Branch | C1: Last commit | D1: Last commit message | E1: Commits not in default | F1: Commits behind default | G1: Unique unmerged changes | H1: Merge status | I1: Note
A2: ATIP-DEV | B2: backup/pre-w24-master | C2: 2026-09-26 | D2: fix(w9): resolve RepoDir inside deploy/rollback scripts (PowerShell 5.1); release RC2 | E2: 0 | F2: 146 | G2: 0 | H2: Fully merged | I2: backup snapshot taken before a wave merge
A3: ATIP-DEV | B3: backup/pre-w25-master | C3: 2026-09-28 | D3: feat(w24): machine learning (ML-01/03/05/06/07/08/09/10/11, MON-05) | E3: 0 | F3: 131 | G3: 0 | H3: Fully merged | I3: backup snapshot taken before a wave merge
A4: ATIP-DEV | B4: backup/pre-w3-align-master | C4: 2026-09-24 | D4: docs(atip): correct the DB backup path in the W3 handoff | E4: 0 | F4: 163 | G4: 0 | H4: Fully merged | I4: backup snapshot taken before a wave merge
A5: ATIP-DEV | B5: backup/pre-w3-master | C5: 2026-09-24 | D5: W2 research & backtesting framework: portfolio engine, metrics, costs, walk-forward | E5: 0 | F5: 167 | G5: 0 | H5: Fully merged | I5: backup snapshot taken before a wave merge
A6: ATIP-DEV | B6: backup/pre-w35-master | C6: 2026-10-02 | D6: chore: add owner documents and the Dhan token refresh tool | E6: 0 | F6: 129 | G6: 0 | H6: Fully merged | I6: backup snapshot taken before a wave merge
A7: ATIP-DEV | B7: backup/pre-w38-master | C7: 2026-10-02 | D7: fix(pipeline): re-run missed / failed jobs instead of only reporting them | E7: 0 | F7: 112 | G7: 0 | H7: Fully merged | I7: backup snapshot taken before a wave merge
A8: ATIP-DEV | B8: backup/pre-w4-master | C8: 2026-09-25 | D8: fix(atip): align W3 with the revised brief | E8: 0 | F8: 162 | G8: 0 | H8: Fully merged | I8: backup snapshot taken before a wave merge
A9: ATIP-DEV | B9: backup/pre-w5-master | C9: 2026-09-25 | D9: docs: update wave 3 and wave 4 handoff | E9: 0 | F9: 159 | G9: 0 | H9: Fully merged | I9: backup snapshot taken before a wave merge
A10: ATIP-DEV | B10: backup/pre-w5b-master | C10: 2026-09-25 | D10: docs: add wave 5 ai ml handoff | E10: 0 | F10: 156 | G10: 0 | H10: Fully merged | I10: backup snapshot taken before a wave merge
A11: ATIP-DEV | B11: backup/pre-w6-master | C11: 2026-09-25 | D11: docs: update wave 5 handoff for the completion pass | E11: 0 | F11: 154 | G11: 0 | H11: Fully merged | I11: backup snapshot taken before a wave merge
A12: ATIP-DEV | B12: backup/pre-w7-master | C12: 2026-09-25 | D12: docs: add wave 6 advanced quant handoff | E12: 0 | F12: 152 | G12: 0 | H12: Fully merged | I12: backup snapshot taken before a wave merge
A13: ATIP-DEV | B13: backup/pre-w8-master | C13: 2026-09-25 | D13: docs: add wave 7 enterprise handoff | E13: 0 | F13: 150 | G13: 0 | H13: Fully merged | I13: backup snapshot taken before a wave merge
... A19: ATIP-DEV | B19: claude/wizardly-curie-fbjeoa | C19: 2026-10-08 | D19: docs(w39b): tracker regenerated after round 3 -- 331 rows, coverage from 1,326 tests | E19: 0 | F19: 9 | G19: 0 | H19: Fully merged | I19: #5 merged
A20: ATIP-DEV | B20: fix-startup-market-catchup | C20: 2026-10-01 | D20: fix(scheduler): catch up missed market-indicator slots at start-up | E20: 1 | F20: 130 | G20: 0 | H20: Merged (same changes already in default)
A21: ATIP-DEV | B21: hotfix-auto-recover | C21: 2026-10-02 | D21: fix(pipeline): re-run missed / failed jobs instead of only reporting them | E21: 0 | F21: 112 | G21: 0 | H21: Fully merged
A22: ATIP-DEV | B22: master | C22: 2026-10-09 | D22: Merge pull request #8: MySQL runtime: translate what cannot translate, quote what MySQL reserves | E22: 0 | F22: 0 | G22: 0 | H22: Default branch
A23: ATIP-DEV | B23: tools-mysql-export | C23: 2026-09-28 | D23: feat(tools): export the SQLite database as MySQL/MariaDB .sql files for phpMyAdmin | E23: 0 | F23: 128 | G23: 0 | H23: Fully merged
A24: ATIP-DEV | B24: w1-foundation | C24: 2026-09-24 | D24: W1 foundation: job monitoring, alerts, P&L, loss limits, sizing, data quality | E24: 0 | F24: 168 | G24: 0 | H24: Fully merged
A25: ATIP-DEV | B25: w11-investor-dna | C25: 2026-09-26 | D25: feat(w11): Investor DNA (ATIP-INV-001) | E25: 0 | F25: 145 | G25: 0 | H25: Fully merged
A26: ATIP-DEV | B26: w12-wealth-dashboard | C26: 2026-09-26 | D26: feat(w12): multi-asset wealth dashboard (ATIP-WLT-001) | E26: 0 | F26: 144 | G26: 0 | H26: Fully merged
A27: ATIP-DEV | B27: w13-goal-planning | C27: 2026-09-26 | D27: feat(w13): goal planning engine (ATIP-GOL-001) | E27: 0 | F27: 143 | G27: 0 | H27: Fully merged
A28: ATIP-DEV | B28: w14-asset-allocation | C28: 2026-09-26 | D28: feat(w14): dynamic asset allocation engine (ATIP-AAL-001) | E28: 0 | F28: 142 | G28: 0 | H28: Fully merged
A29: ATIP-DEV | B29: w15-5-performance-attribution | C29: 2026-09-26 | D29: feat(w15.5): investor performance attribution (ATIP-PERF-001) | E29: 0 | F29: 140 | G29: 0 | H29: Fully merged
A30: ATIP-DEV | B30: w15-rebalancing | C30: 2026-09-26 | D30: feat(w15): portfolio rebalancing engine (ATIP-RBL-001) | E30: 0 | F30: 141 | G30: 0 | H30: Fully merged
A31: ATIP-DEV | B31: w16-ai-advisor | C31: 2026-09-26 | D31: feat(w16): explainable AI investment advisor (ATIP-AIA-001) | E31: 0 | F31: 139 | G31: 0 | H31: Fully merged
... A43: ATIP-DEV | B43: w27-data-scores | C43: 2026-10-01 | D43: feat(w27): data and scores (DP-15, SC-13, SC-02, DP-16, SC-14, SC-06, DP-12, DP-01, AD-03, DB-04) | E43: 0 | F43: 127 | G43: 0 | H43: Fully merged
A44: ATIP-DEV | B44: w28-signals-news-dashboards | C44: 2026-10-01 | D44: feat(w28): signals, news intelligence and dashboards (SG-08, DB-11, DB-16, SE-05, NS-02..06, DB-06, DB-18) | E44: 1 | F44: 128 | G44: 1 | H44: NOT merged | I44: superseded: W28 merged via w28-strategy-ai
A45: ATIP-DEV | B45: w28-strategy-ai | C45: 2026-10-01 | D45: feat(w28): strategy and AI (SG-08, DB-11, DB-16, SE-05, NS-02, NS-03, NS-04, DB-06, DB-18) | E45: 0 | F45: 126 | G45: 0 | H45: Fully merged
A46: ATIP-DEV | B46: w28b-news-weighting | C46: 2026-10-01 | D46: feat(w28b): news weighting and announcement NLP (NS-05, NS-06) | E46: 0 | F46: 119 | G46: 0 | H46: Fully merged
A47: ATIP-DEV | B47: w29-execution | C47: 2026-10-01 | D47: feat(w29): execution (EX-02, EX-08, BR-05, BR-06, RK-17, BR-08, EX-09, EX-10, BR-02, MON-04, SEC-03) | E47: 0 | F47: 125 | G47: 0 | H47: Fully merged
A48: ATIP-DEV | B48: w3-strategy-engine | C48: 2026-09-25 | D48: fix(atip): align W3 with the revised brief | E48: 0 | F48: 162 | G48: 0 | H48: Fully merged
A49: ATIP-DEV | B49: w30-advanced-quant | C49: 2026-10-01 | D49: feat(w30): advanced quant (AF-05, QR-10, QR-05, QR-06, QR-09, AF-07) | E49: 0 | F49: 124 | G49: 0 | H49: Fully merged
A50: ATIP-DEV | B50: w31-production-hardening | C50: 2026-10-01 | D50: feat(w31): production hardening (OPS-06, SEC-04, API-05, OPS-05, OPS-10, OPS-11) | E50: 0 | F50: 123 | G50: 0 | H50: Fully merged
A51: ATIP-DEV | B51: w32-enterprise-saas | C51: 2026-10-01 | D51: W32: enterprise SaaS -- merge W9 SaaS layer, recovery codes, capital accounting, intraday alerts, webhook consumers | E51: 0 | F51: 121 | G51: 0 | H51: Fully merged
A52: ATIP-DEV | B52: w33-wealth-qa | C52: 2026-10-02 | D52: docs: add owner tracker and planning workbooks | E52: 1 | F52: 120 | G52: 1 | H52: NOT merged | I52: W33 merged; 1 extra commit adds 4 old owner workbooks
A53: ATIP-DEV | B53: w34-execution-microstructure | C53: 2026-10-01 | D53: feat(w34): execution microstructure (EX-11, EX-12, EX-15, EX-16, BT-17) | E53: 0 | F53: 118 | G53: 0 | H53: Fully merged
A54: ATIP-DEV | B54: w35-data-platform | C54: 2026-10-02 | D54: fix(wealth): defects found by running the wealth test suite (486/486 pass) | E54: 0 | F54: 115 | G54: 0 | H54: Fully merged
A55: ATIP-DEV | B55: w36-ml-strategy-tooling | C55: 2026-10-02 | D55: feat(w36): ML and strategy tooling (ML-02, ML-04, ML-16, SE-10, AF-06, API-06) | E55: 0 | F55: 112 | G55: 0 | H55: Fully merged
A56: ATIP-DEV | B56: w37-brokers-multi-asset | C56: 2026-10-02 | D56: feat(w37): brokers and multi-asset (ENT-06, BR-07, PF-12, ENT-15) | E56: 0 | F56: 111 | G56: 0 | H56: Fully merged
A57: ATIP-DEV | B57: w38-platform-compliance | C57: 2026-10-02 | D57: feat(w38): compliance monitoring, data privacy, mobile PWA, regulatory register | E57: 0 | F57: 106 | G57: 0 | H57: Fully merged
A58: ATIP-DEV | B58: w38-secrets-vault | C58: 2026-10-02 | D58: fix(secrets): make the vault migration safe; order controls pass in paper mode | E58: 0 | F58: 105 | G58: 0 | H58: Fully merged
A59: ATIP-DEV | B59: w4-risk-execution | C59: 2026-09-25 | D59: docs: update wave 3 and wave 4 handoff | E59: 0 | F59: 159 | G59: 0 | H59: Fully merged
A60: ATIP-DEV | B60: w5-ai-ml | C60: 2026-09-25 | D60: docs: update wave 5 handoff for the completion pass | E60: 0 | F60: 154 | G60: 0 | H60: Fully merged
A61: ATIP-DEV | B61: w6-advanced-quant | C61: 2026-09-25 | D61: docs: add wave 6 advanced quant handoff | E61: 0 | F61: 152 | G61: 0 | H61: Fully merged
A62: ATIP-DEV | B62: w7-enterprise | C62: 2026-09-25 | D62: docs: add wave 7 enterprise handoff | E62: 0 | F62: 150 | G62: 0 | H62: Fully merged
A63: ATIP-DEV | B63: w8-production-hardening | C63: 2026-09-26 | D63: docs: W8 production hardening handoff, operations and security docs, tracker | E63: 0 | F63: 148 | G63: 0 | H63: Fully merged
A64: ATIP-DEV | B64: w9-enterprise-saas | C64: 2026-09-26 | D64: wip(w9-saas): park incomplete enterprise-SaaS work (superseded by the revised W9 brief) | E64: 0 | F64: 147 | G64: 0 | H64: Fully merged
A65: ATIP-DEV | B65: w9-release | C65: 2026-09-26 | D65: fix(w9): resolve RepoDir inside deploy/rollback scripts (PowerShell 5.1); release RC2 | E65: 0 | F65: 146 | G65: 0 | H65: Fully merged
A66: bkesari | B66: claude/amazing-cannon-5n3fro | C66: 2026-10-08 | D66: Serve Milk & Dairy under /milk, and fix a build that would have failed | E66: 0 | F66: 9 | G66: 0 | H66: Fully merged | I66: #9 merged
A67: bkesari | B67: claude/awesome-dijkstra-fmccpl | C67: 2026-10-09 | D67: Give the test database a migrate command of its own | E67: 1 | F67: 0 | G67: 1 | H67: NOT merged | I67: #14 open, #10 merged
A68: bkesari | B68: claude/charming-edison-ofoncf | C68: 2026-10-08 | D68: Fix the admin dashboard's 500, and make the documented local setup work | E68: 0 | F68: 4 | G68: 0 | H68: Fully merged | I68: #12 merged, #11 merged, #8 merged
A69: bkesari | B69: main | C69: 2026-10-09 | D69: Merge pull request #13: fill blank test secrets too, so tests pass after cp .env.example .env | E69: 0 | F69: 0 | G69: 0 | H69: Default branch
A70: bkesari | B70: staging | C70: 2026-09-01 | D70: Rebrand Bkesari to GoKesari, move support/grievance emails to gokesari.com | E70: 0 | F70: 23 | G70: 0 | H70: Fully merged | I70: #7 merged, #6 merged
A71: bkesari-platform | B71: claude/amazing-cannon-5n3fro | C71: 2026-10-08 | D71: Serve Education at /edu/ by stripping the prefix and rebuilding it in the app | E71: 0 | F71: 12 | G71: 0 | H71: Fully merged | I71: #2 merged
A72: bkesari-platform | B72: claude/awesome-dijkstra-fmccpl | C72: 2026-10-09 | D72: Run the database tests on MySQL, the client production actually uses | E72: 1 | F72: 0 | G72: 1 | H72: NOT merged | I72: #5 open, #1 merged
A73: bkesari-platform | B73: dev | C73: 2026-10-02 | D73: Document the three-tier dev/test/production deployment pipeline | E73: 0 | F73: 19 | G73: 0 | H73: Fully merged
A74: bkesari-platform | B74: main | C74: 2026-10-09 | D74: Merge pull request #4: local MySQL setup script, and the Mac guide and status workbook brought up to date | E74: 0 | F74: 0 | G74: 0 | H74: Default branch
A75: bkesari-platform | B75: staging | C75: 2026-10-02 | D75: Document the three-tier dev/test/production deployment pipeline | E75: 0 | F75: 19 | G75: 0 | H75: Fully merged

Sheet Test Runs
A1: Repo / app | B1: Command | C1: Result on 2026-10-09 | D1: Environment
A2: ATIP-DEV (master, after PR #8) | B2: python -m pytest | C2: PASS: 1,336 passed, 42 skipped, 0 failed (the merged tree; CI pytest + image green) | D2: Linux container (not macOS): Python 3.13.16, Node 22.22, PHP 8.3.6, MySQL 8.0.46
A3: ATIP-DEV (before today's merges) | B3: python -m pytest | C3: PASS: 1,321 passed, 36 skipped | D3: Linux container (not macOS): Python 3.13.16, Node 22.22, PHP 8.3.6, MySQL 8.0.46
A4: bkesari (main, now MySQL) | B4: tools/setup_local_mysql.sh: db:migrate + db:seed into bk_milk / bk_milk_test | C4: PASS: 52 tables each, 373 products, 5 demo shops | D4: Linux container (not macOS): Python 3.13.16, Node 22.22, PHP 8.3.6, MySQL 8.0.46
A5: bkesari | B5: npm test against bk_milk_test | C5: PASS: 284/284 on main with #12 and #13 merged, both with the setup script's .env and with a .env copied from .env.example (before #13: 270/281). typecheck clean, eslint 0 errors | D5: Linux container (not macOS): Python 3.13.16, Node 22.22, PHP 8.3.6, MySQL 8.0.46
A6: bkesari | B6: npm run dev | C6: PASS: / and /shops answer 200 and list the seeded shops from MySQL | D6: Linux container (not macOS): Python 3.13.16, Node 22.22, PHP 8.3.6, MySQL 8.0.46
A7: bkesari | B7: npm run test:e2e | C7: Not run (needs a browser session) | D7: -
A8: bkesari-platform portal (main) | B8: npm test | C8: PASS: 44 node tests + 32 deploy-guard cases (CI green) | D8: Linux container (not macOS): Python 3.13.16, Node 22.22, PHP 8.3.6, MySQL 8.0.46
A9: bkesari-platform portal | B9: node --env-file=.env portal/server.js (MySQL bk_portal) | C9: PASS: / 200, /tasks/ 401 without login, a project created through the API is stored in bk_portal | D9: Linux container (not macOS): Python 3.13.16, Node 22.22, PHP 8.3.6, MySQL 8.0.46
A10: bkesari-platform edu/ (main) | B10: php artisan test | C10: PASS: 387 tests (CI edu job green) | D10: Linux container (not macOS): Python 3.13.16, Node 22.22, PHP 8.3.6, MySQL 8.0.46
A11: bkesari-platform edu/ | B11: migrate --seed into bk_edu; php artisan serve | C11: PASS: 74 tables; /, /schools/1 and /login answer 200 | D11: Linux container (not macOS): Python 3.13.16, Node 22.22, PHP 8.3.6, MySQL 8.0.46
A12: tools/setup_local_mysql.sh | B12: fresh run, then a second run | C12: PASS: creates 6 databases and users, writes 3 .env files, migrates and seeds; the re-run reuses passwords and seeds nothing twice; a user cannot read another site's database | D12: Linux container (not macOS): Python 3.13.16, Node 22.22, PHP 8.3.6, MySQL 8.0.46

Sheet Legend
A1: Value | B1: Meaning
A2: Phase | B2: ATIP: the tracker's own phases 0-11 (docs/ATIP_MASTER_TRACKER.csv), plus 12 for the macOS / database PRs the tracker does not carry. Education: edu/ROADMAP.md's phases 1-8, plus 9 for modules built after them and 10 for multilingual. Milk & Dairy and the portal record no phases, so they are grouped by delivery date and pull request.
A3: Phase status | B3: COMPLETED: every feature completed. BUILT - VERIFICATION PENDING: everything built and merged, independent QA / UAT still to do. IN PROGRESS: something is not started, in progress, blocked or in an open PR (blocked and in-review counts are shown). NOT STARTED: nothing built yet.
A4: COMPLETED | B4: Built and merged. ATIP: verified per its tracker. bkesari / Education: their automated test suites pass (see Test Runs).
A5: IMPLEMENTED BUT NOT VERIFIED | B5: Built and merged with automated tests; independent QA / owner UAT still pending (ATIP's own vocabulary).
A6: BLOCKED | B6: Partly built; waits on an owner decision, credential or legal sign-off.
A7: IN PROGRESS | B7: Being worked on.
A8: IN REVIEW (open PR) / (draft PR) | B8: Code exists on a branch with a pull request; NOT merged into the default branch.
A9: SUPERSEDED | B9: Branch-only work that was replaced by something already merged; nothing to do.
A10: NOT STARTED | B10: Documented as deferred in the repo's roadmap; no code yet.
A11: On GitHub default branch? | B11: Yes = the change is on master (ATIP-DEV) or main (bkesari, bkesari-platform) on GitHub.
A12: Local Git (fresh clone) | B12: State of a fresh clone made today, which mirrors GitHub. Commits that exist only on your Mac are not visible here; run tools/check_local_git.sh on the Mac.
... A15: NOT merged (Branches) | B15: The branch has changes that are not in the default branch.
